Workbook

Sheet Hướng dẫn
B2: FER202 — AI Log Template | Project Nhóm
B3: Hướng dẫn sử dụng | FPT University
B5: 📌 MỤC ĐÍCH
B6: File này dùng để gì? | C6: Ghi lại nhật ký sử dụng AI của nhóm trong suốt project môn FER202 — theo từng tuần.
B7: Ai điền? | C7: Mỗi thành viên tự điền phần của mình vào các bảng của tuần tương ứng. Trưởng nhóm tổng hợp và upload.
B8: Nộp khi nào? | C8: Cuối mỗi tuần (hoặc theo deadline giảng viên). Một file duy nhất cho cả học kỳ.
B10: 📁 CÁC SHEET TRONG FILE
B11: Thông tin nhóm | C11: Điền 1 lần đầu học kỳ: tên nhóm, MSSV, phân công, mô tả project.
B12: Week_01 → Week_10 | C12: Mỗi tuần có 4 bảng: AI_Audit_Log, Changelog, Prompts, Reflection.
B13: Summary | C13: Tổng hợp tự động (công thức) số lần dùng AI, mức hỗ trợ theo từng tuần/thành viên.
B15: 📝 4 BẢNG TRONG MỖI TUẦN
B16: BẢNG 1 — AI_AUDIT_LOG | C16: Ghi mỗi lần dùng AI: ngày, ai dùng, tool, mục đích, mức hỗ trợ, đã chỉnh sửa gì, kiểm chứng.
B17: BẢNG 2 — CHANGELOG | C17: Ghi thay đổi project trong tuần (Added / Changed / Fixed / Removed). Không bắt buộc gắn với AI.
B18: BẢNG 3 — PROMPTS | C18: Ghi chi tiết từng prompt quan trọng đã dùng: nội dung, kết quả AI trả về, cách nhóm sử dụng/chỉnh sửa.
B19: BẢNG 4 — REFLECTION | C19: Mỗi thành viên viết 1 block suy ngẫm cá nhân cuối tuần (đã làm gì, AI hỗ trợ ra sao, điểm chưa tốt).
B21: ✅ QUY ƯỚC
B22: Cột TV | C22: Dùng ký hiệu A / B / C / D / E (khớp với bảng Thông tin nhóm).
B23: Mức hỗ trợ AI | C23: Low = AI gợi ý nhỏ | Medium = AI đóng góp đáng kể | High = AI tạo phần lớn nội dung
B24: Loại Changelog | C24: Added = thêm mới | Changed = cải tiến | Fixed = sửa lỗi | Removed = xóa bỏ
B25: (*) bắt buộc | C25: Các cột đánh dấu (*) là bắt buộc phải điền.

Sheet Thông tin nhóm
B2: THÔNG TIN NHÓM — FER202
B3: 📋 Thông tin lớp
B4: Mã lớp học | C4: FER202_SE20A07
B5: Giảng viên | C5: Lê Thị Bích Tra — traltb@fe.edu.vn
B6: Học kỳ / Năm học | C6: SU26
B7: Tên nhóm | C7: 36-38-75_gr
B8: Số thành viên | C8: 5
B10: 👥 Danh sách thành viên
B11: Ký hiệu (*) | C11: Họ và tên (*) | D11: MSSV (*) | E11: Email (*) | F11: Vai trò | G11: Ghi chú
B12: A | C12: Lê Thị Văn Anh | D12: DE19 | F12: Trưởng nhóm
B13: B | C13: Trần Quốc Sang | D13: DE190983 | E13: tqsang1435@gmail.com | F13: Thành viên
B14: C | F14: Thành viên
B15: D | F15: Thành viên
B16: E | F16: Thành viên
B18: 💡 Mô tả dự án
B19: Tên hệ thống | C19: ATELIER — Supercar Showroom
B20: Mô tả ngắn | C20: Website giới thiệu showroom siêu xe với giao diện tối, hiện đại. Hệ thống hiển thị xe nổi bật, danh sách siêu xe, thương hiệu xe, thông tin cơ bản của xe, thanh điều hướng và khu vực liên hệ.
B21: Công nghệ sử dụng | C21: React, JavaScript (JSX), CSS, Vite.
B22: Link repo (GitHub/GitLab) | C22: https://github.com/fudn-traltb-su26/rbl-fer202-theotuan-36-38-75_gr.git
B23: Link Jira
B24: Link demo

Sheet Week_01
B2: WEEK 01 — Nhật ký AI & Project
B3: Mỗi thành viên dùng ký hiệu A/B/C/D/E ở cột TV. Cột (*) bắt buộc điền. Lưu file sau khi điền xong.
B5: 📋 BẢNG 1: Nhật ký sử dụng AI (AI_AUDIT_LOG)
B6: Ghi mỗi lần dùng AI vào 1 dòng. Mức hỗ trợ: Low = AI gợi ý nhỏ | Medium = AI đóng góp nhiều | High = AI tạo phần lớn
B7: Ngày (*) | C7: TV (*) | D7: Công cụ AI (*) | E7: Mục đích sử dụng (*) | F7: File ảnh hưởng | G7: Mức hỗ trợ (*) | H7: Đã chỉnh sửa gì? | I7: Kiểm chứng
B8: 05/05/2026 | C8: A | D8: ChatGPT-4o | E8: Tư vấn cấu trúc thư mục React 18 + Vite cho showroom siêu xe | F8: src/ | G8: Low | H8: Bỏ các thư mục state management chưa dùng, cấu hình folder component và page | I8: Đúng chuẩn cấu trúc, npm run dev chạy mượt
B9: 05/05/2026 | C9: B | D9: Google Stitch | E9: Generate mockup Trang chủ + Brand list cho showroom siêu xe | F9: docs/mockup/HomePage | G9: High | H9: Lựa chọn layout tối giản luxury, bổ sung lưới grid 3 cột cho card siêu xe | I9: Layout cân đối, màu tối sang trọng
B10: 06/05/2026 | C10: C | D10: Figma Make | E10: Tạo prototype tương tác giữa So sánh xe và Chi tiết xe | F10: docs/mockup/ComparePage | G10: High | H10: Căn chỉnh khoảng cách các cột thông số, thiết kế responsive | I10: Tương tác nhấp chọn xe hiển thị trực quan
B11: 06/05/2026 | C11: D | D11: ChatGPT-4o | E11: Thiết kế cấu trúc file db.json gồm hãng xe, danh mục xe, thông số kỹ thuật chi tiết | F11: db.json | G11: Medium | H11: Thêm trường topSpeedKmh, acceleration0to100, engineCC để phục vụ so sánh | I11: json-server chạy GET trả đúng cấu trúc
B12: 07/05/2026 | C12: E | D12: Claude | E12: Vẽ sơ đồ Component Tree từ mockup Figma của showroom siêu xe | F12: docs/component-tree.md | G12: Medium | H12: Thêm component ComparePanel và FilterSidebar dùng chung | I12: Khớp 100% với mockup thiết kế
B13: 08/05/2026 | C13: A | D13: GitHub Copilot | E13: Sinh README.md skeleton + .gitignore cho dự án | F13: README.md | G13: Low | H13: Viết lại mô tả, thêm hướng dẫn chạy json-server và mock data | I13: Render đúng trên GitHub
B17: 📝 BẢNG 2: Nhật ký thay đổi project (CHANGELOG)
B18: Added = thêm mới | Changed = cải tiến | Fixed = sửa lỗi | Removed = xóa bỏ
B19: Loại (*) | C19: TV (*) | D19: Mô tả thay đổi (*) | G19: File liên quan | I19: Ghi chú
B20: Added — Thêm mới
C21: A | D21: Khởi tạo repo rbl-fer202-theotuan: React 18, Vite, react-bootstrap | G21: package.json, src/ | I21: npm run dev OK
C22: D | D22: Thiết lập cấu trúc db.json với 10 siêu xe mẫu đầy đủ thông số kỹ thuật | G22: db.json | I22: Format chuẩn REST API
C23: B | D23: Thiết kế và xuất 17 mockup màn hình PNG showroom | G23: docs/mockup/ | I23: Đã export sang Figma
B24: Changed — Cải tiến
C25: E | D25: Cập nhật Component Tree v2: Tách biệt SidebarFilters làm component riêng | G25: docs/component-tree.md | I25: Dễ bảo trì
C26: C | D26: Thống nhất style guide: tone màu đen sang trọng (#08080a) và vàng champagne (#c5a880) | G26: docs/mockup/style-guide.md | I26: Khớp mockup FIGMA
B28: Fixed — Sửa lỗi
C29: D | D29: Đổi định dạng price trong db.json từ dạng string sang số nguyên | G29: db.json | I29: Phát hiện khi test json-server
C30: B | D30: Sửa mockup Trang chủ: Bổ sung nút Compare chuyên biệt trên header | G30: docs/mockup/ | I30: Khớp checklist
B32: Removed — Xóa bỏ
B37: 💡 BẢNG 3: Nhật ký Prompt AI (PROMPTS)
B38: Mỗi prompt quan trọng ghi 1 block gồm 4 dòng. Ghi rõ prompt đã dùng, kết quả, cách nhóm sử dụng, và kiểm chứng.
B39: Prompt # | C39: TV | D39: Công cụ AI | E39: Prompt đã dùng (nguyên văn) (*)
B40: Prompt #1 (B — Google Stitch) | E40: Design a dark luxury homepage for a supercar showroom named ATELIER. Black background, gold accents, navigation header, hero carousel, brand logos, featured cars section.
B41: Kết quả AI trả về và vấn đề gặp phải: | E41: Layout đẹp nhưng ảnh xe bị lệch tỉ lệ, thiếu nút So sánh nhanh.
B42: Nhóm đã chỉnh sửa / sử dụng như thế nào: | E42: Chỉnh sửa prompt: use exact aspect ratio 16:9 for car cards, add dark overlay gradient. Thêm nút Compare vào Header.
B43: Kiểm chứng (test pass/fail, kết quả đúng không): | E43: Đối chiếu checklist requirements: đủ 6/6 component chính, nhóm duyệt làm chuẩn UI.
B44: Prompt #2 (D — ChatGPT-4o) | E44: Thiết kế cấu trúc db.json cho json-server của showroom siêu xe gồm các model nổi tiếng: Ferrari, Lamborghini, Bugatti, Porsche, McLaren. Mỗi xe cần đầy đủ trường horsepower, torque, price, topSpeedKmh, acceleration0to100.
B45: Kết quả AI trả về và vấn đề gặp phải: | E45: AI sinh đúng trường nhưng giá trị topSpeed là dạng dặm/giờ (mph), và rating vượt thang 5.
B46: Nhóm đã chỉnh sửa / sử dụng như thế nào: | E46: Đổi sang km/h, chuẩn hóa acceleration là số thực, clamp rating <= 5.
B47: Kiểm chứng (test pass/fail, kết quả đúng không): | E47: Các trường số lọc và sắp xếp chính xác qua URL parameters của json-server.
B48: Prompt #3 (E — Claude) | E48: Vẽ Component Tree dạng văn bản cho dự án Showroom siêu xe Atelier gồm: HomePage, CarListPage, ComparePage, CarDetailPage.
B49: Kết quả AI trả về và vấn đề gặp phải: | E49: AI chia quá nhiều component vụn vặt gây khó quản lý, thiếu layout footer.
B50: Nhóm đã chỉnh sửa / sử dụng như thế nào: | E50: Gộp các card thông số nhỏ thành component SpecTable dùng chung. Thêm layout Header/Footer chung.
B51: Kiểm chứng (test pass/fail, kết quả đúng không): | E51: Component tree rõ ràng, dễ phân công cho các thành viên code tuần 2.
... B55: Kiểm chứng (test pass/fail, kết quả đúng không): | E55: npm create vite chạy thành công, dev server khởi động nhanh < 1s.
B57: 🪞 BẢNG 4: Suy ngẫm cuối tuần (REFLECTION)
B58: Mỗi thành viên điền 1 block riêng. Mục 'AI sai/thiếu' bắt buộc ≥ 2 ví dụ cụ thể. Viết thành câu đầy đủ.
B59: Thành viên A — Trưởng nhóm
B60: Đã làm gì trong tuần này? (*) | E60: Tạo GitHub repo, cấu hình Vite project, cài react-bootstrap/router/axios, viết README.
B61: AI đã hỗ trợ như thế nào? | E61: ChatGPT-4o tư vấn cấu trúc thư mục và so sánh Vite/CRA; Copilot sinh README skeleton.
B62: AI sai hoặc thiếu ở đâu? (*) | E62: (1) AI đề xuất CRA cũ kĩ. (2) Cấu trúc thư mục AI đề xuất có Redux ngay tuần 1 quá sớm so với lộ trình môn.
B63: Khó khăn gặp phải | E63: Conflict phiên bản giữa bootstrap 5 và react-bootstrap khi cài đặt.
B64: Nếu làm lại, sẽ cải thiện điều gì? | E64: Ghi rõ phiên bản React 18, react-bootstrap 2.x ngay trong prompt để AI trả lời đúng ngữ cảnh.
B66: Thành viên B — Thành viên
B67: Đã làm gì trong tuần này? (*) | E67: Thiết kế mockup Trang chủ, danh sách hãng xe bằng Google Stitch theo workflow.
B68: AI đã hỗ trợ như thế nào? | E68: Stitch tạo layout nhanh, giúp nhóm định hình phong cách màu đen sang trọng champagne gold.
B69: AI sai hoặc thiếu ở đâu? (*) | E69: (1) Ảnh xe bị méo tỷ lệ ở lưới grid. (2) Thiếu nút Compare và giỏ hàng trên Header.
B70: Khó khăn gặp phải | E70: Mô tả chi tiết giao diện bằng tiếng Anh để AI sinh ra chính xác.
B71: Nếu làm lại, sẽ cải thiện điều gì? | E71: Chuẩn bị danh sách yêu cầu UI trước khi bắt đầu prompt để tránh lặp lại nhiều lần.
B73: Thành viên C — Thành viên
B74: Đã làm gì trong tuần này? (*) | E74: Mockup trang so sánh và chi tiết xe bằng Figma; thống nhất style guide màu sắc nhóm.
B75: AI đã hỗ trợ như thế nào? | E75: Figma Make giúp sinh prototype chuyển đổi mượt mà giữa các trang.
B76: AI sai hoặc thiếu ở đâu? (*) | E76: (1) Sinh trang checkout không nằm trong phạm vi dự án. (2) Bảng so sánh bị thừa cột.
B77: Khó khăn gặp phải | E77: Độ rộng cột so sánh thông số xe bị hẹp khi xem trên màn hình nhỏ.
B78: Nếu làm lại, sẽ cải thiện điều gì? | E78: Chỉ định rõ số lượng cột và kích thước cột ngay trong mô tả prompt đầu tiên.
B80: Thành viên D — Thành viên
B81: Đã làm gì trong tuần này? (*) | E81: Thiết kế db.json với các thực thể xe, hãng xe, tin tức; seed 10 siêu xe mẫu và chạy thử json-server.
B82: AI đã hỗ trợ như thế nào? | E82: ChatGPT-4o sinh dữ liệu mẫu nhanh, chính xác tên các siêu xe nổi tiếng thế giới.
B83: AI sai hoặc thiếu ở đâu? (*) | E83: (1) Giá tiền sinh dạng string có chữ USD không tính toán được. (2) Rating có giá trị vượt quá 5.
B84: Khó khăn gặp phải | E84: Xử lý các liên kết khóa ngoại giữa bảng xe và bảng hãng sản xuất.
B85: Nếu làm lại, sẽ cải thiện điều gì? | E85: Định nghĩa schema dữ liệu chi tiết trước khi yêu cầu AI sinh dữ liệu mẫu.
B87: Thành viên E — Thành viên
B88: Đã làm gì trong tuần này? (*) | E88: Vẽ sơ đồ Component Tree, tổng hợp prompt log cả nhóm và cập nhật README.
B89: AI đã hỗ trợ như thế nào? | E89: Claude vẽ cây component dạng văn bản rất rõ ràng, giải thích cách gom nhóm component.
B90: AI sai hoặc thiếu ở đâu? (*) | E90: (1) Claude tách nhỏ component CarCard không cần thiết. (2) Quên các layout dùng chung như Header/Footer.
B91: Khó khăn gặp phải | E91: Tổng hợp tài liệu từ nhiều nguồn thiết kế khác nhau của các bạn trong nhóm.
B92: Nếu làm lại, sẽ cải thiện điều gì? | E92: Thống nhất cấu trúc tài liệu trước để các thành viên gửi thông tin đồng bộ.
B94: FER202 | Week 01 | FPT University — Điền xong nhớ Ctrl+S để lưu!

Sheet Week_02
B2: WEEK 01 — Nhật ký AI & Project
B3: Mỗi thành viên dùng ký hiệu A/B/C/D/E ở cột TV. Cột (*) bắt buộc điền. Lưu file sau khi điền xong.
B5: 📋 BẢNG 1: Nhật ký sử dụng AI (AI_AUDIT_LOG)
B6: Ghi mỗi lần dùng AI vào 1 dòng. Mức hỗ trợ: Low = AI gợi ý nhỏ | Medium = AI đóng góp nhiều | High = AI tạo phần lớn
B7: Ngày (*) | C7: TV (*) | D7: Công cụ AI (*) | E7: Mục đích sử dụng (*) | F7: File ảnh hưởng | G7: Mức hỗ trợ (*) | H7: Đã chỉnh sửa gì? | I7: Kiểm chứng
B8: 12/05/2026 | C8: A | D8: ChatGPT-4o | E8: Giải thích cách render logo ATELIER bằng SVG động trong React component | F8: src/components/Navbar.jsx | G8: Low | H8: Tạo component Navbar tĩnh với menu điều hướng, logo và nút đăng nhập | I8: Thanh menu hiển thị chuẩn, không có lỗi JSX
B9: 12/05/2026 | C9: B | D9: GitHub Copilot | E9: Gợi ý code map() hiển thị danh sách 6 chiếc siêu xe đầu tiên trên trang chủ | F9: src/components/CarGrid.jsx | G9: High | H9: Viết component CarGrid nhận mảng xe tĩnh và render danh sách CarCard | I9: Hiển thị đúng 6 card xe dạng lưới
B10: 13/05/2026 | C10: C | D10: ChatGPT-4o | E10: Hướng dẫn viết CSS cho card xe hiệu ứng dark-glass sang trọng | F10: src/components/CarCard.css | G10: Medium | H10: Thiết kế visual cho CarCard: nền mờ, bo góc, viền nhẹ gold champagne | I10: Giao diện card bóng mịn, sang trọng
B11: 13/05/2026 | C11: D | D11: Claude | E11: Tư vấn cấu trúc layout dùng chung | F11: src/App.jsx | G11: Low | H11: Ghép nối Navbar, Footer, Banner và CarGrid vào App.jsx | I11: Trang chủ hiển thị đầy đủ bố cục tĩnh
C12: VAN_ANH | D12: ChatGPT | E12: Hỗ trợ xây dựng Navbar, Footer và bố cục giao diện chung. | F12: src/components/Navbar.jsx, src/components/Navbar.css, src/components/Footer.jsx, src/components/Footer.css | G12: Medium | H12: Tạo logo ATELIER, menu điều hướng, thông tin liên hệ và phần footer cuối trang. | I12: Kiểm tra Navbar và Footer hiển thị trên trang, không bị vỡ bố cục cơ bản.
C13: VAN_ANH | D13: ChatGPT | E13: Hỗ trợ tích hợp các component vào giao diện chính của ứng dụng. | F13: src/App.jsx, src/pages/HomePage.jsx | G13: Medium | H13: Gắn Navbar, Banner, BrandCard, CarGrid và Footer vào bố cục trang chủ. | I13: Mở trang chủ và kiểm tra các khu vực hiển thị theo thứ tự mong muốn.
B17: 📝 BẢNG 2: Nhật ký thay đổi project (CHANGELOG)
B18: Added = thêm mới | Changed = cải tiến | Fixed = sửa lỗi | Removed = xóa bỏ
B19: Loại (*) | C19: TV (*) | D19: Mô tả thay đổi (*) | G19: File liên quan | I19: Ghi chú
B20: Added — Thêm mới
C21: A | D21: Tạo Navbar.jsx và Footer.jsx tĩnh tích hợp layout | E21: Tạo Banner cho trang chủ showroom với ảnh nền, overlay tối, tiêu đề, slogan và các nút hành động. | G21: Navbar.jsx, Footer.jsx | H21: src/components/Banner.jsx; src/components/Banner.css | I21: Khớp thiết kế
C22: B | D22: Tạo Banner.jsx hiển thị ảnh bìa showroom siêu xe nổi bật | E22: Tạo CarCard, CarGrid và BrandCard để hiển thị danh sách xe và thương hiệu bằng component JSX. | G22: Banner.jsx | H22: src/components/CarCard.jsx; src/components/CarCard.css; src/components/CarGrid.jsx; src/components/CarGrid.css; src/components/BrandCard.jsx; src/components/BrandCard.css | I22: Chạy offline
C23: B | D23: Tạo CarCard.jsx và CarGrid.jsx để hiển thị lưới danh sách xe | E23: Tạo Navbar, Footer và tích hợp các component vào giao diện chính của ứng dụng. | G23: CarCard.jsx, CarGrid.jsx | H23: src/components/Navbar.jsx; src/components/Navbar.css; src/components/Footer.jsx; src/components/Footer.css; src/App.jsx | I23: Sử dụng mockup
B24: Changed — Cải tiến
C25: C | D25: Cấu hình style CSS variables trong index.css cho dark-glass theme | E25: Điều chỉnh CSS cho Card và Grid để giao diện tối, dễ đọc và có hiệu ứng hover. | G25: src/index.css | H25: src/components/CarCard.css; src/components/CarGrid.css; src/index.css | I25: Luxury theme
C26: A | D26: Sửa lỗi JSX đóng thẻ không đúng ở component Footer | G26: Footer.jsx | I26: Phát hiện khi compile
B28: Fixed — Sửa lỗi
C29: B | D29: Sửa lỗi import sai đường dẫn ảnh cục bộ của các hãng xe | G29: src/data/cars.js | I29: Fixed path
B32: Removed — Xóa bỏ
B37: 💡 BẢNG 3: Nhật ký Prompt AI (PROMPTS)
B38: Mỗi prompt quan trọng ghi 1 block gồm 4 dòng. Ghi rõ prompt đã dùng, kết quả, cách nhóm sử dụng, và kiểm chứng.
B39: Prompt # | C39: TV | D39: Công cụ AI | E39: Prompt đã dùng (nguyên văn) (*)
B40: Prompt #1 (A — ChatGPT-4o) | E40: Write a responsive React component for a navigation header of a luxury car website named ATELIER. Include navigation links, search input and a gold login button. Use react-bootstrap.
B41: Kết quả AI trả về và vấn đề gặp phải: | E41: AI sử dụng các component Bootstrap cũ và không export mặc định.
B42: Nhóm đã chỉnh sửa / sử dụng như thế nào: | E42: Thay thế bằng cú pháp ES6 import mới, định hình lại màu sắc gold champagne.
B43: Kiểm chứng (test pass/fail, kết quả đúng không): | E43: Header responsive trên mobile ẩn menu vào nút toggle đúng chuẩn.
B44: Prompt #2 (B — GitHub Copilot) | E44: Write a React component named CarGrid that takes a list of cars and displays them in a 3-column grid layout using react-bootstrap Rows and Cols.
B45: Kết quả AI trả về và vấn đề gặp phải: | E45: Copilot sinh grid bị lệch dòng do kích thước ảnh xe không đồng đều.
B46: Nhóm đã chỉnh sửa / sử dụng như thế nào: | E46: Thêm thuộc tính h-100 vào CarCard và đặt class object-fit-cover cho hình ảnh xe.
B47: Kiểm chứng (test pass/fail, kết quả đúng không): | E47: Lưới xe tự động căn chỉnh hoàn hảo bất kể kích thước ảnh gốc.
B48: Prompt #3 (C — ChatGPT-4o) | E48: Write a CSS stylesheet for a dark theme luxury card. Give it a subtle gradient background, gold borders, rounded corners, blur backdrop, and shadow effects.
B49: Kết quả AI trả về và vấn đề gặp phải: | E49: CSS quá sáng, không ra chất luxury black mà ra màu xám phẳng.
B50: Nhóm đã chỉnh sửa / sử dụng như thế nào: | E50: Sử dụng background: rgba(24, 26, 31, 0.5) kết hợp với border: 1px solid rgba(255, 255, 255, 0.08).
B51: Kiểm chứng (test pass/fail, kết quả đúng không): | E51: Đúng phong cách dark-glass óng ánh có chiều sâu.
... B55: Kiểm chứng (test pass/fail, kết quả đúng không): | E55: npm run dev biên dịch thành công, hiển thị trang chủ tĩnh hoàn chỉnh.
B57: 🪞 BẢNG 4: Suy ngẫm cuối tuần (REFLECTION)
B58: Mỗi thành viên điền 1 block riêng. Mục 'AI sai/thiếu' bắt buộc ≥ 2 ví dụ cụ thể. Viết thành câu đầy đủ.
B59: Thành viên A — Trưởng nhóm: VAN_ANH
B60: Đã làm gì trong tuần này? (*) | E60: Code Navbar, Footer và ghép nối trang chủ tĩnh.
B61: AI đã hỗ trợ như thế nào? | E61: AI hỗ trợ viết HTML cấu trúc menu bootstrap nhanh.
B62: AI sai hoặc thiếu ở đâu? (*) | E62: (1) AI quên import React. (2) Link logo bị hardcode dẫn đến lỗi tải trang.
B63: Khó khăn gặp phải | E63: Căn chỉnh khoảng cách giữa logo và menu trên các màn hình khác nhau.
B64: Nếu làm lại, sẽ cải thiện điều gì? | E64: Sử dụng Container của bootstrap để tự động căn lề thay vì tự viết CSS.
B66: Thành viên B — Thành viên : SANG
B67: Đã làm gì trong tuần này? (*) | E67: Code Banner, CarCard, CarGrid và chuẩn bị dữ liệu mock offline.
B68: AI đã hỗ trợ như thế nào? | E68: Copilot gợi ý code lặp mảng cực nhanh, giúp hoàn thành grid xe trong 10 phút.
B69: AI sai hoặc thiếu ở đâu? (*) | E69: (1) Card xe bị vỡ khi tiêu đề xe quá dài. (2) Ảnh xe không tự co giãn.
B70: Khó khăn gặp phải | E70: Xử lý hình ảnh tỉ lệ 16:9 trên card siêu xe.
B71: Nếu làm lại, sẽ cải thiện điều gì? | E71: Sử dụng class tỉ lệ của bootstrap để giữ ảnh xe cân đối.
B73: Thành viên C — Thành viên
B74: Đã làm gì trong tuần này? (*) | E74: Thiết kế CSS cho các components, tạo các class dark-glass chung.
B75: AI đã hỗ trợ như thế nào? | E75: AI hỗ trợ viết các thuộc tính box-shadow và backdrop-filter chuẩn xác.
B76: AI sai hoặc thiếu ở đâu? (*) | E76: (1) CSS gợi ý màu vàng quá chói. (2) Backdrop filter không chạy trên Firefox do thiếu prefix.
B77: Khó khăn gặp phải | E77: Làm sao để màu đen có chiều sâu chứ không bị đen phẳng lì.
B78: Nếu làm lại, sẽ cải thiện điều gì? | E78: Sử dụng các lớp radial-gradient và linear-gradient lồng nhau.
B80: Thành viên D — Thành viên
B81: Đã làm gì trong tuần này? (*) | E81: Hỗ trợ ghép nối layouts, test hiển thị responsive.
B82: AI đã hỗ trợ như thế nào? | E82: AI gợi ý các media queries chuẩn cho các thiết bị di động.
B83: AI sai hoặc thiếu ở đâu? (*) | E83: (1) Grid 3 cột trên mobile bị ép quá hẹp. (2) Margin bị lệch ở màn hình iPad.
B84: Khó khăn gặp phải | E84: Đồng bộ giao diện khi gộp code của A và B lại.
B85: Nếu làm lại, sẽ cải thiện điều gì? | E85: Thống nhất dùng class bootstrap col-12 col-md-6 col-lg-4 để tự động responsive.
B87: Thành viên E — Thành viên
B88: Đã làm gì trong tuần này? (*) | E88: Viết báo cáo tuần 2, tổng hợp prompt log thiết kế.
B89: AI đã hỗ trợ như thế nào? | E89: AI hỗ trợ sửa lỗi diễn đạt, làm báo cáo ngắn gọn súc tích.
B90: AI sai hoặc thiếu ở đâu? (*) | E90: (1) AI viết quá dài dòng. (2) Mô tả kỹ thuật bị sai thuật ngữ React.
B91: Khó khăn gặp phải | E91: Theo dõi tiến độ của các thành viên trong nhóm để ghi log chính xác.
B92: Nếu làm lại, sẽ cải thiện điều gì? | E92: Lập file tracking online để mọi người tự cập nhật công việc cuối ngày.
B94: FER202 | Week 02 | FPT University — Điền xong nhớ Ctrl+S để lưu!

Sheet Week_03
B2: WEEK 01 — Nhật ký AI & Project
B3: Mỗi thành viên dùng ký hiệu A/B/C/D/E ở cột TV. Cột (*) bắt buộc điền. Lưu file sau khi điền xong.
B5: 📋 BẢNG 1: Nhật ký sử dụng AI (AI_AUDIT_LOG)
B6: Ghi mỗi lần dùng AI vào 1 dòng. Mức hỗ trợ: Low = AI gợi ý nhỏ | Medium = AI đóng góp nhiều | High = AI tạo phần lớn
B7: Ngày (*) | C7: TV (*) | D7: Công cụ AI (*) | E7: Mục đích sử dụng (*) | F7: File ảnh hưởng | G7: Mức hỗ trợ (*) | H7: Đã chỉnh sửa gì? | I7: Kiểm chứng
B8: 19/05/2026 | C8: C | D8: ChatGPT-4o | E8: Gợi ý cách viết component SpecTable nhận đối tượng specs qua props | F8: src/components/SpecTable.jsx | G8: High | H8: Xây dựng bảng thông số kỹ thuật siêu xe (Mã lực, Mô-men xoắn, Tốc độ tối đa) | I8: Bảng thông số hiển thị đẹp mắt, khớp dữ liệu props
B9: 19/05/2026 | C9: D | D9: Claude | E9: Thiết kế component SectionWrapper nhận title và props.children | F9: src/components/SectionWrapper.jsx | G9: Medium | H9: Tạo wrapper bọc các section chính (Siêu xe nổi bật, Hãng xe đối tác) | I9: Các phân vùng hiển thị thống nhất
B10: 20/05/2026 | C10: A | D10: GitHub Copilot | E10: Viết hàm callback click truyền từ App xuống CarCard thông qua props | F10: src/components/CarCard.jsx | G10: Low | H10: Truyền thông tin xe và hàm chọn so sánh xe qua props | I10: Click vào card xe nhận diện đúng ID
B11: 20/05/2026 | C11: B | D11: ChatGPT-4o | E11: Tạo component BrandCard nhận props hãng xe để hiển thị logo | F11: src/components/BrandCard.jsx | G11: Low | H11: Dựng danh sách logo hãng xe trên trang chủ | I11: Click hãng xe chuyển trang đúng
B17: 📝 BẢNG 2: Nhật ký thay đổi project (CHANGELOG)
B18: Added = thêm mới | Changed = cải tiến | Fixed = sửa lỗi | Removed = xóa bỏ
B19: Loại (*) | C19: TV (*) | D19: Mô tả thay đổi (*) | G19: File liên quan | I19: Ghi chú
B20: Added — Thêm mới
C21: C | D21: Tạo SpecTable.jsx hiển thị chi tiết thông số kỹ thuật xe | G21: SpecTable.jsx | I21: Dùng props
C22: D | D22: Tạo SectionWrapper.jsx để tái sử dụng khung phân vùng tiêu đề | G22: SectionWrapper.jsx | I22: Children props
C23: B | D23: Tạo BrandCard.jsx hiển thị danh sách hãng siêu xe | G23: BrandCard.jsx | I23: Mockup brand
B24: Changed — Cải tiến
C25: C | D25: Refactor CarCard và CarGrid để nhận và truyền dữ liệu qua Props | G25: CarCard.jsx, CarGrid.jsx | I25: Động hóa dữ liệu
C26: D | D26: Vẽ sơ đồ Data Flow truyền dữ liệu từ App xuống các component con | G26: docs/data-flow.md | I26: Sơ đồ chi tiết
B28: Fixed — Sửa lỗi
C29: A | D29: Sửa lỗi props.children không hiển thị do viết sai cú pháp render | G29: SectionWrapper.jsx | I29: Fix JSX syntax
C30: C | D30: Sửa lỗi kiểu dữ liệu props truyền vào SpecTable bị sai định dạng | G30: SpecTable.jsx | I30: Fix type check
B32: Removed — Xóa bỏ
B37: 💡 BẢNG 3: Nhật ký Prompt AI (PROMPTS)
B38: Mỗi prompt quan trọng ghi 1 block gồm 4 dòng. Ghi rõ prompt đã dùng, kết quả, cách nhóm sử dụng, và kiểm chứng.
B39: Prompt # | C39: TV | D39: Công cụ AI | E39: Prompt đã dùng (nguyên văn) (*)
B40: Prompt #1 (C — ChatGPT-4o) | E40: Write a React component named SpecTable that takes a "specs" object via props (containing horsepower, torque, topSpeedKmh, acceleration0to100, engineType) and renders a clean key-value table.
B41: Kết quả AI trả về và vấn đề gặp phải: | E41: AI viết bảng HTML trơn, trông rất thô và không hợp tông màu tối.
B42: Nhóm đã chỉnh sửa / sử dụng như thế nào: | E42: Nhúng các style CSS dark-glass, căn lề phải cho các giá trị thông số.
B43: Kiểm chứng (test pass/fail, kết quả đúng không): | E43: Bảng thông số hiển thị đẹp mắt, tự co giãn theo card xe.
B44: Prompt #2 (D — Claude) | E44: Create a reusable React wrapper component named SectionWrapper that takes "title" and renders it above its props.children. Wrap it in a Container.
B45: Kết quả AI trả về và vấn đề gặp phải: | E45: Claude viết thừa class CSS không tồn tại ở dự án.
B46: Nhóm đã chỉnh sửa / sử dụng như thế nào: | E46: Loại bỏ các style class thừa, sử dụng Container của react-bootstrap.
B47: Kiểm chứng (test pass/fail, kết quả đúng không): | E47: Các section của trang chủ được bọc đồng bộ, code ngắn đi 40 dòng.
B48: Prompt #3 (A — GitHub Copilot) | E48: Show how to pass a click handler function from a parent component to a child CarCard component via props, so clicking a button in child calls parent function with car ID.
B49: Kết quả AI trả về và vấn đề gặp phải: | E49: Copilot gợi ý dùng inline arrow function làm giảm hiệu năng render.
B50: Nhóm đã chỉnh sửa / sử dụng như thế nào: | E50: Viết lại hàm handle click riêng biệt ở component cha và truyền ref qua props.
B51: Kiểm chứng (test pass/fail, kết quả đúng không): | E51: Bắt sự kiện click chính xác, không gây re-render thừa.
... B55: Kiểm chứng (test pass/fail, kết quả đúng không): | E55: Hiển thị logo mượt mà, tự động thay thế bằng chữ nếu link ảnh hỏng.
B57: 🪞 BẢNG 4: Suy ngẫm cuối tuần (REFLECTION)
B58: Mỗi thành viên điền 1 block riêng. Mục 'AI sai/thiếu' bắt buộc ≥ 2 ví dụ cụ thể. Viết thành câu đầy đủ.
B59: Thành viên A — Trưởng nhóm
B60: Đã làm gì trong tuần này? (*) | E60: Hỗ trợ các thành viên refactor code props, kiểm tra cú pháp JSX.
B61: AI đã hỗ trợ như thế nào? | E61: AI giúp viết nhanh các prop check và gợi ý các cấu trúc ES6 destructuring.
B62: AI sai hoặc thiếu ở đâu? (*) | E62: (1) AI đề xuất prop-types thư viện ngoài không cần thiết. (2) Gợi ý sai tên biến.
B63: Khó khăn gặp phải | E63: Xử lý lỗi truyền sai kiểu dữ liệu giữa các cấp component.
B64: Nếu làm lại, sẽ cải thiện điều gì? | E64: Thống nhất kiểu dữ liệu cho specs (đều là số thực/số nguyên).
B66: Thành viên B — Thành viên
B67: Đã làm gì trong tuần này? (*) | E67: Code component BrandCard, dựng layout danh sách hãng xe.
B68: AI đã hỗ trợ như thế nào? | E68: AI hỗ trợ viết các CSS hover hiệu ứng phát sáng vàng champagne gold.
B69: AI sai hoặc thiếu ở đâu? (*) | E69: (1) AI thiết lập ảnh logo quá to. (2) Hiệu ứng hover bị giật trên màn hình nhỏ.
B70: Khó khăn gặp phải | E70: Căn chỉnh khoảng cách giữa các logo hãng xe đối tác.
B71: Nếu làm lại, sẽ cải thiện điều gì? | E71: Sử dụng thuộc tính transition trong CSS để hiệu ứng hover mượt hơn.
B73: Thành viên C — Thành viên
B74: Đã làm gì trong tuần này? (*) | E74: Code SpecTable, refactor CarCard và CarGrid dùng props động.
B75: AI đã hỗ trợ như thế nào? | E75: AI giúp viết mã JSX động rất nhanh, gom nhóm thông số xe gọn gàng.
B76: AI sai hoặc thiếu ở đâu? (*) | E76: (1) Bảng thông số bị tràn viền khi màn hình co lại. (2) AI viết sai chính tả trường specs.
B77: Khó khăn gặp phải | E77: Hiển thị các thông số có đơn vị đo lường khác nhau (mã lực, Nm, km/h).
B78: Nếu làm lại, sẽ cải thiện điều gì? | E78: Định dạng đơn vị đo ngay trong SpecTable để component cha chỉ cần truyền số.
B80: Thành viên D — Thành viên
B81: Đã làm gì trong tuần này? (*) | E81: Code SectionWrapper, vẽ sơ đồ truyền props Data Flow.
B82: AI đã hỗ trợ như thế nào? | E82: AI hỗ trợ vẽ sơ đồ dạng text rất trực quan để chuyển thể sang file Markdown.
B83: AI sai hoặc thiếu ở đâu? (*) | E83: (1) Claude vẽ thiếu cấp truyền props từ Grid xuống Card. (2) Mô tả sai hướng đi của data.
B84: Khó khăn gặp phải | E84: Tạo khung wrapper linh hoạt cho nhiều kiểu nội dung (card xe, logo hãng).
B85: Nếu làm lại, sẽ cải thiện điều gì? | E85: Sử dụng thuộc tính children linh hoạt kết hợp flexbox.
B87: Thành viên E — Thành viên
B88: Đã làm gì trong tuần này? (*) | E88: Viết báo cáo tuần 3, kiểm tra tài liệu Component Tree.
B89: AI đã hỗ trợ như thế nào? | E89: AI hỗ trợ tóm tắt các thay đổi lớn trong tuần chính xác.
B90: AI sai hoặc thiếu ở đâu? (*) | E90: (1) AI bỏ qua mô tả của Sơn. (2) Viết sai tên file SpecTable.
B91: Khó khăn gặp phải | E91: Tổng hợp báo cáo tuần đúng hạn khi các bạn nộp code muộn.
B92: Nếu làm lại, sẽ cải thiện điều gì? | E92: Nhắc nhở nhóm cam kết thời gian hoàn thành task trước 2 ngày.
B94: FER202 | Week 03 | FPT University — Điền xong nhớ Ctrl+S để lưu!

Sheet Week_04
B2: WEEK 01 — Nhật ký AI & Project
B3: Mỗi thành viên dùng ký hiệu A/B/C/D/E ở cột TV. Cột (*) bắt buộc điền. Lưu file sau khi điền xong.
B5: 📋 BẢNG 1: Nhật ký sử dụng AI (AI_AUDIT_LOG)
B6: Ghi mỗi lần dùng AI vào 1 dòng. Mức hỗ trợ: Low = AI gợi ý nhỏ | Medium = AI đóng góp nhiều | High = AI tạo phần lớn
B7: Ngày (*) | C7: TV (*) | D7: Công cụ AI (*) | E7: Mục đích sử dụng (*) | F7: File ảnh hưởng | G7: Mức hỗ trợ (*) | H7: Đã chỉnh sửa gì? | I7: Kiểm chứng
B8: 26/05/2026 | C8: C | D8: ChatGPT-4o | E8: Gợi ý cách cập nhật mảng danh sách xe so sánh (tối đa 2 xe) bằng useState | F8: src/App.jsx | G8: High | H8: Xây dựng tính năng chọn xe vào danh sách so sánh từ CarCard | I8: Chọn tối đa 2 xe, chọn xe thứ 3 sẽ báo lỗi hoặc ghi đè
B9: 26/05/2026 | C9: D | D9: Claude | E9: Tạo form tìm kiếm có kiểm soát (Controlled Component) nhập tên siêu xe | F9: src/components/Navbar.jsx | G9: Medium | H9: Tích hợp ô tìm kiếm trên Navbar cập nhật state từ khóa | I9: Nhập chữ đâu lọc danh sách xe ngay tại đó
B10: 27/05/2026 | C10: B | D10: GitHub Copilot | E10: Viết hàm lọc danh sách xe theo brandId và khoảng giá | F10: src/pages/CarListPage.jsx | G10: Medium | H10: Dựng bộ lọc bên sidebar: lọc hãng xe, bộ lọc giá kéo slider | I10: Danh sách xe lọc động theo thời gian thực
B11: 27/05/2026 | C11: A | D11: ChatGPT-4o | E11: Giải thích cơ chế lifting state up để đồng bộ state tìm kiếm giữa các page | F11: src/App.jsx | G11: Low | H11: Đồng bộ từ khóa tìm kiếm toàn cục | I11: Navbar và Grid xe hiển thị chung từ khóa
B17: 📝 BẢNG 2: Nhật ký thay đổi project (CHANGELOG)
B18: Added = thêm mới | Changed = cải tiến | Fixed = sửa lỗi | Removed = xóa bỏ
B19: Loại (*) | C19: TV (*) | D19: Mô tả thay đổi (*) | G19: File liên quan | I19: Ghi chú
B20: Added — Thêm mới
C21: C | D21: Tạo ComparePanel hiển thị nhanh 2 xe đang được chọn so sánh | G21: ComparePanel.jsx | I21: State dynamic
C22: B | D22: Tạo SidebarFilters với bộ lọc hãng, khoảng giá và loại xe | G22: SidebarFilters.jsx | I22: Interactive filter
C23: C | D23: Quản lý state compareCars và searchKeyword tại App.jsx (Lifting State Up) | G23: App.jsx | I23: State lifting
B24: Changed — Cải tiến
C25: D | D25: Tạo bộ lọc giá kéo thanh slider cập nhật khoảng giá động | G25: SidebarFilters.jsx | I25: Gold slider styling
C26: A | D26: Đồng bộ state tìm kiếm giữa ô input trên Navbar và kết quả lọc xe | G26: Navbar.jsx, App.jsx | I26: Real-time search
B28: Fixed — Sửa lỗi
C29: D | D29: Sửa lỗi gõ tiếng Việt ô tìm kiếm bị mất ký tự do lag render state | G29: Navbar.jsx | I29: Debounce input
C30: C | D30: Sửa lỗi so sánh trùng 1 xe khi click nhanh 2 lần liên tục | G30: App.jsx | I30: Unique check validation
B32: Removed — Xóa bỏ
B37: 💡 BẢNG 3: Nhật ký Prompt AI (PROMPTS)
B38: Mỗi prompt quan trọng ghi 1 block gồm 4 dòng. Ghi rõ prompt đã dùng, kết quả, cách nhóm sử dụng, và kiểm chứng.
B39: Prompt # | C39: TV | D39: Công cụ AI | E39: Prompt đã dùng (nguyên văn) (*)
B40: Prompt #1 (C — ChatGPT-4o) | E40: Write a state update function in React to handle adding a car to a compare list. The list can have at most 2 unique cars. If the user clicks a car already in the list, remove it.
B41: Kết quả AI trả về và vấn đề gặp phải: | E41: AI viết hàm cập nhật mutate trực tiếp mảng state cũ.
B42: Nhóm đã chỉnh sửa / sử dụng như thế nào: | E42: Sử dụng cú pháp copy mảng [...prev] và hàm filter để trả về mảng mới sạch sẽ.
B43: Kiểm chứng (test pass/fail, kết quả đúng không): | E43: Click chọn xe: thêm vào mảng; click lại: xóa đi; tối đa 2 xe hoạt động chuẩn.
B44: Prompt #2 (D — Claude) | E44: Write a controlled input component in React for a search bar. It should call an onChange function passed from parent on every keystroke.
B45: Kết quả AI trả về và vấn đề gặp phải: | E45: Claude đề xuất dùng useRef dẫn đến input bị mất kiểm soát state.
B46: Nhóm đã chỉnh sửa / sử dụng như thế nào: | E46: Chuyển sang dùng value và onChange liên kết trực tiếp với state ở component cha.
B47: Kiểm chứng (test pass/fail, kết quả đúng không): | E47: Từ khóa gõ vào cập nhật tức thì lên console và lọc danh sách xe đúng.
B48: Prompt #3 (B — GitHub Copilot) | E48: Write a JavaScript filter function that filters an array of car objects based on selected brandIds (array of numbers), drivetrain (array of strings), and price range [min, max].
B49: Kết quả AI trả về và vấn đề gặp phải: | E49: Copilot quên xử lý trường hợp mảng brandIds rỗng (không lọc gì cả).
B50: Nhóm đã chỉnh sửa / sử dụng như thế nào: | E50: Bổ sung điều kiện: if brandIds.length === 0, cho qua toàn bộ các hãng xe.
B51: Kiểm chứng (test pass/fail, kết quả đúng không): | E51: Bộ lọc sidebar hoạt động đúng, không bị trắng màn hình khi bỏ chọn tất cả.
... B55: Kiểm chứng (test pass/fail, kết quả đúng không): | E55: Thanh trượt giá có màu champagne gold sang trọng, viền vàng óng ánh.
B57: 🪞 BẢNG 4: Suy ngẫm cuối tuần (REFLECTION)
B58: Mỗi thành viên điền 1 block riêng. Mục 'AI sai/thiếu' bắt buộc ≥ 2 ví dụ cụ thể. Viết thành câu đầy đủ.
B59: Thành viên A — Trưởng nhóm
B60: Đã làm gì trong tuần này? (*) | E60: Đồng bộ state tìm kiếm toàn cục, review code event handlers.
B61: AI đã hỗ trợ như thế nào? | E61: AI giải thích cặn kẽ mô hình Lifting State Up giúp nhóm hiểu rõ luồng dữ liệu.
B62: AI sai hoặc thiếu ở đâu? (*) | E62: (1) AI gợi ý cài Redux để quản lý tìm kiếm — quá nặng cho app tĩnh. (2) Viết sai cú pháp pass prop.
B63: Khó khăn gặp phải | E63: Đồng bộ từ khóa tìm kiếm từ Navbar xuống danh sách xe ở HomePage.
B64: Nếu làm lại, sẽ cải thiện điều gì? | E64: Lưu state keyword ở App, truyền giá trị và setter xuống Navbar và Grid.
B66: Thành viên B — Thành viên
B67: Đã làm gì trong tuần này? (*) | E67: Code component SidebarFilters, xử lý sự kiện thay đổi bộ lọc.
B68: AI đã hỗ trợ như thế nào? | E68: Copilot gợi ý code lọc mảng nhanh, bao quát được nhiều điều kiện lọc.
B69: AI sai hoặc thiếu ở đâu? (*) | E69: (1) AI đề xuất hàm lọc không tối ưu (lặp mảng nhiều lần). (2) Sai điều kiện lọc khoảng giá.
B70: Khó khăn gặp phải | E70: Thiết kế giao diện sidebar có nhiều checkbox và slider mà vẫn gọn gàng.
B71: Nếu làm lại, sẽ cải thiện điều gì? | E71: Sử dụng Accordion của bootstrap để thu gọn các nhóm bộ lọc.
B73: Thành viên C — Thành viên
B74: Đã làm gì trong tuần này? (*) | E74: Code ComparePanel hiển thị nhanh xe chọn, quản lý state so sánh.
B75: AI đã hỗ trợ như thế nào? | E75: AI gợi ý cách viết hàm toggle thêm/xóa xe trong mảng rất ngắn gọn.
B76: AI sai hoặc thiếu ở đâu? (*) | E76: (1) AI quên kiểm tra trùng ID xe. (2) Giao diện panel bị đè lên các card xe khác.
B77: Khó khăn gặp phải | E77: Giới hạn danh sách so sánh chỉ có tối đa 2 xe và hiển thị thông báo nếu quá.
B78: Nếu làm lại, sẽ cải thiện điều gì? | E78: Bổ sung cảnh báo toast khi người dùng cố tình thêm xe thứ 3.
B80: Thành viên D — Thành viên
B81: Đã làm gì trong tuần này? (*) | E81: Cập nhật controlled search bar trên Navbar, thiết kế CSS cho slider.
B82: AI đã hỗ trợ như thế nào? | E82: AI hỗ trợ viết CSS styling cho thanh trượt slider champagne gold bóng bẩy.
B83: AI sai hoặc thiếu ở đâu? (*) | E83: (1) Sự kiện input bị delay khi gõ nhanh bằng Telex. (2) Nút xóa từ khóa hoạt động sai.
B84: Khó khăn gặp phải | E84: Khắc phục hiện tượng lag giật khi gõ từ khóa tìm kiếm.
B85: Nếu làm lại, sẽ cải thiện điều gì? | E85: Tách state input cục bộ và debounce trước khi cập nhật lên state chung.
B87: Thành viên E — Thành viên
B88: Đã làm gì trong tuần này? (*) | E88: Tổng hợp tài liệu tuần 4, kiểm tra lỗi UI cùng nhóm.
B89: AI đã hỗ trợ như thế nào? | E89: AI giúp viết tài liệu mô tả các tương tác động khoa học, rõ ràng.
B90: AI sai hoặc thiếu ở đâu? (*) | E90: (1) AI viết sai tên sự kiện onChange. (2) Bỏ qua mô tả của bộ lọc giá.
B91: Khó khăn gặp phải | E91: Kiểm chứng toàn bộ các trường hợp test-case của bộ lọc.
B92: Nếu làm lại, sẽ cải thiện điều gì? | E92: Vẽ bảng ma trận test để các bạn tự đối chiếu chức năng trước khi nộp code.
B94: FER202 | Week 04 | FPT University — Điền xong nhớ Ctrl+S để lưu!

Sheet Week_05
B2: WEEK 01 — Nhật ký AI & Project
B3: Mỗi thành viên dùng ký hiệu A/B/C/D/E ở cột TV. Cột (*) bắt buộc điền. Lưu file sau khi điền xong.
B5: 📋 BẢNG 1: Nhật ký sử dụng AI (AI_AUDIT_LOG)
B6: Ghi mỗi lần dùng AI vào 1 dòng. Mức hỗ trợ: Low = AI gợi ý nhỏ | Medium = AI đóng góp nhiều | High = AI tạo phần lớn
B7: Ngày (*) | C7: TV (*) | D7: Công cụ AI (*) | E7: Mục đích sử dụng (*) | F7: File ảnh hưởng | G7: Mức hỗ trợ (*) | H7: Đã chỉnh sửa gì? | I7: Kiểm chứng
B8: 02/06/2026 | C8: A | D8: ChatGPT-4o | E8: Xây dựng bảng so sánh 2 cột động đối chiếu đầy đủ các thông số của 2 xe được chọn | F8: src/pages/ComparePage.jsx | G8: High | H8: Thiết kế trang so sánh xe (ComparePage) hiển thị song song 2 xe | I8: Hiển thị so sánh trực quan động cơ, giá, mã lực, tốc độ
B9: 02/06/2026 | C9: C | D9: Claude | E9: Gợi ý hiệu ứng hover champagne gold cho các dòng thông số chênh lệch hơn | F9: src/pages/ComparePage.css | G9: Medium | H9: Styling trang ComparePage theo phong cách tối giản luxury black | I9: Giao diện bảng so sánh cực kỳ sang trọng, cân đối
B10: 03/06/2026 | C10: E | D10: ChatGPT-4o | E10: Tạo dropdown chọn xe trực tiếp tại trang ComparePage để thay đổi xe so sánh nhanh | F10: src/pages/ComparePage.jsx | G10: Medium | H10: Tích hợp 2 ô Dropdown ở đầu mỗi cột so sánh | I10: Chọn xe từ dropdown cập nhật ngay thông tin cột đó
B11: 03/06/2026 | C11: B | D11: GitHub Copilot | E11: Viết hàm ẩn/hiện các dòng thông số giống nhau để tập trung so sánh điểm khác | F11: src/pages/ComparePage.jsx | G11: Low | H11: Thêm bộ lọc "Chỉ xem điểm khác biệt" trên bảng so sánh | I11: Click checkbox ẩn đi các dòng trùng thông số
B17: 📝 BẢNG 2: Nhật ký thay đổi project (CHANGELOG)
B18: Added = thêm mới | Changed = cải tiến | Fixed = sửa lỗi | Removed = xóa bỏ
B19: Loại (*) | C19: TV (*) | D19: Mô tả thay đổi (*) | G19: File liên quan | I19: Ghi chú
B20: Added — Thêm mới
C21: A | D21: Tạo ComparePage.jsx hiển thị chi tiết bảng so sánh 2 siêu xe | G21: ComparePage.jsx | I21: Bảng động
C22: C | D22: Thiết kế file style ComparePage.css hỗ trợ dark theme bóng bẩy | G22: ComparePage.css | I22: Glossy style
C23: E | D23: Tích hợp dropdown chọn nhanh siêu xe trực tiếp trên cột so sánh | G23: ComparePage.jsx | I23: Dropdown selection
B24: Changed — Cải tiến
C25: B | D25: Thêm tính năng ẩn các thông số giống nhau giữa 2 xe | G25: ComparePage.jsx | I25: Filter differences
C26: A | D26: Tạo nút Clear All để xóa nhanh cả hai xe đang so sánh về trạng thái trống | G26: ComparePage.jsx | I26: Clear state
B28: Fixed — Sửa lỗi
C29: A | D29: Sửa lỗi trang ComparePage bị vỡ layout khi chưa chọn đủ 2 xe | G29: ComparePage.jsx | I29: Placeholder UI
C30: E | D30: Sửa lỗi dropdown không cập nhật đúng model xe khi thay đổi hãng sản xuất | G30: ComparePage.jsx | I30: Dropdown sync
B32: Removed — Xóa bỏ
B37: 💡 BẢNG 3: Nhật ký Prompt AI (PROMPTS)
B38: Mỗi prompt quan trọng ghi 1 block gồm 4 dòng. Ghi rõ prompt đã dùng, kết quả, cách nhóm sử dụng, và kiểm chứng.
B39: Prompt # | C39: TV | D39: Công cụ AI | E39: Prompt đã dùng (nguyên văn) (*)
B40: Prompt #1 (A — ChatGPT-4o) | E40: Create a comparison page component in React called ComparePage. It should take two selected car objects and render their specifications side-by-side. If one or both cars are missing, render a placeholder card with a button to select a car.
B41: Kết quả AI trả về và vấn đề gặp phải: | E41: AI viết mã hiển thị bị null reference error khi truy cập các trường sâu trong specs của xe trống.
B42: Nhóm đã chỉnh sửa / sử dụng như thế nào: | E42: Thêm các kiểm tra điều kiện (optional chaining: car?.specs?.horsepower) và render giao diện chọn xe.
B43: Kiểm chứng (test pass/fail, kết quả đúng không): | E43: Bảng hiển thị hoàn hảo, khi thiếu xe sẽ hiện ô nét đứt vàng champagne hướng dẫn chọn xe.
B44: Prompt #2 (C — Claude) | E44: Write CSS rules for a comparison table. We need a dark theme, semi-transparent row backgrounds, champagne gold highlights on hover, and a sticky header for the car images.
B45: Kết quả AI trả về và vấn đề gặp phải: | E45: Claude viết CSS làm cho bảng bị tràn chiều rộng màn hình thiết bị.
B46: Nhóm đã chỉnh sửa / sử dụng như thế nào: | E46: Thêm wrapper div có thuộc tính overflow-x: auto bao quanh table.
B47: Kiểm chứng (test pass/fail, kết quả đúng không): | E47: Bảng cuộn ngang mượt mà trên điện thoại, ảnh xe cố định trên đầu cột khi cuộn.
B48: Prompt #3 (E — ChatGPT-4o) | E48: Create a selection dropdown inside the comparison page header for each column, allowing users to choose a supercar from a list of available cars to replace the current column.
B49: Kết quả AI trả về và vấn đề gặp phải: | E49: AI gợi ý dùng thẻ <select> thô của HTML nhìn rất xấu, lệch tone luxury.
B50: Nhóm đã chỉnh sửa / sử dụng như thế nào: | E50: Sử dụng Dropdown component của react-bootstrap kết hợp custom toggle CSS.
B51: Kiểm chứng (test pass/fail, kết quả đúng không): | E51: Dropdown tùy chọn siêu xe mượt mà, đồng bộ lập tức thông số cột bên dưới.
... B55: Kiểm chứng (test pass/fail, kết quả đúng không): | E55: Tính năng lọc điểm khác biệt hoạt động chính xác, ẩn nhanh các dòng trùng nhau.
B57: 🪞 BẢNG 4: Suy ngẫm cuối tuần (REFLECTION)
B58: Mỗi thành viên điền 1 block riêng. Mục 'AI sai/thiếu' bắt buộc ≥ 2 ví dụ cụ thể. Viết thành câu đầy đủ.
B59: Thành viên A — Trưởng nhóm
B60: Đã làm gì trong tuần này? (*) | E60: Code ComparePage, xử lý binding dữ liệu so sánh xe, viết placeholder UI.
B61: AI đã hỗ trợ như thế nào? | E61: AI hỗ trợ viết các câu lệnh điều kiện render giao diện chọn xe trực quan.
B62: AI sai hoặc thiếu ở đâu? (*) | E62: (1) AI quên xử lý trường hợp mảng cars rỗng gây crash trang. (2) CSS đề xuất bị đè lòe loẹt.
B63: Khó khăn gặp phải | E63: Bố trí cột so sánh cân đối, tránh lệch dòng giữa các tiêu chí thông số.
B64: Nếu làm lại, sẽ cải thiện điều gì? | E64: Sử dụng cấu trúc bảng HTML chuẩn (tr, td) thay vì các khối div flexbox tự chế.
B66: Thành viên B — Thành viên
B67: Đã làm gì trong tuần này? (*) | E67: Thêm tính năng ẩn các dòng trùng thông số, kiểm thử logic chọn xe.
B68: AI đã hỗ trợ như thế nào? | E68: Copilot gợi ý code so sánh đối tượng nhanh, viết logic lọc khác biệt trong 5 phút.
B69: AI sai hoặc thiếu ở đâu? (*) | E69: (1) AI bị nhầm lẫn giữa brandId và tên hãng xe thực tế. (2) Viết thừa hàm bổ trợ.
B70: Khó khăn gặp phải | E70: Xử lý so sánh các trường phức tạp như mảng màu sắc xe.
B71: Nếu làm lại, sẽ cải thiện điều gì? | E71: Chuyển mảng màu sắc thành chuỗi cách nhau bởi dấu phẩy trước khi đối chiếu.
B73: Thành viên C — Thành viên
B74: Đã làm gì trong tuần này? (*) | E74: Styling trang ComparePage, thêm hiệu ứng dark-glass óng ánh và sticky header.
B75: AI đã hỗ trợ như thế nào? | E75: AI gợi ý các thuộc tính backdrop-filter và box-shadow viền vàng champagne rất đẹp.
B76: AI sai hoặc thiếu ở đâu? (*) | E76: (1) Nền bảng bị quá tối làm chữ đen khó đọc — phải đổi chữ sang trắng xám. (2) Sticky bị lệch vị trí.
B77: Khó khăn gặp phải | E77: Căn chỉnh bảng so sánh hiển thị responsive trên các dòng điện thoại thông minh.
B78: Nếu làm lại, sẽ cải thiện điều gì? | E78: Thiết lập min-width cho các cột so sánh để đảm bảo nội dung không bị ép chữ.
B80: Thành viên D — Thành viên
B81: Đã làm gì trong tuần này? (*) | E81: Hỗ trợ kiểm thử, chuẩn bị mockup khớp code thực tế.
B82: AI đã hỗ trợ như thế nào? | E82: AI hỗ trợ viết các kịch bản kiểm thử biên (không chọn xe, chọn 1 xe, chọn 2 xe giống nhau).
B83: AI sai hoặc thiếu ở đâu? (*) | E83: (1) AI đề xuất kịch bản kiểm thử quá cơ bản. (2) Thiếu kiểm chứng responsive.
B84: Khó khăn gặp phải | E84: Khớp các dữ liệu hãng xe và thông số kỹ thuật thực tế theo db.json.
B85: Nếu làm lại, sẽ cải thiện điều gì? | E85: Xem xét các thông số kỹ thuật thực tế để đảm bảo tính logic (ví dụ xe hybrid có 2 loại động cơ).
B87: Thành viên E — Thành viên
B88: Đã làm gì trong tuần này? (*) | E88: Code dropdown chọn siêu xe trực tiếp trên cột so sánh, làm báo cáo tuần 5.
B89: AI đã hỗ trợ như thế nào? | E89: AI hỗ trợ viết nhanh dropdown selection và sync state lên component cha.
B90: AI sai hoặc thiếu ở đâu? (*) | E90: (1) AI viết sai cú pháp prop eventKey của Dropdown. (2) Dropdown bị che mất bởi table overlay.
B91: Khó khăn gặp phải | E91: Đồng bộ dữ liệu dropdown khi danh sách xe thay đổi.
B92: Nếu làm lại, sẽ cải thiện điều gì? | E92: Thiết lập z-index cho dropdown menu để luôn nổi trên bảng so sánh.
B94: FER202 | Week 05 | FPT University — Điền xong nhớ Ctrl+S để lưu!

Sheet Week_06
B2: WEEK 01 — Nhật ký AI & Project
B3: Mỗi thành viên dùng ký hiệu A/B/C/D/E ở cột TV. Cột (*) bắt buộc điền. Lưu file sau khi điền xong.
B5: 📋 BẢNG 1: Nhật ký sử dụng AI (AI_AUDIT_LOG)
B6: Ghi mỗi lần dùng AI vào 1 dòng. Mức hỗ trợ: Low = AI gợi ý nhỏ | Medium = AI đóng góp nhiều | High = AI tạo phần lớn
B7: Ngày (*) | C7: TV (*) | D7: Công cụ AI (*) | E7: Mục đích sử dụng (*) | F7: File ảnh hưởng | G7: Mức hỗ trợ (*) | H7: Đã chỉnh sửa gì? | I7: Kiểm chứng
B8: 09/06/2026 | C8: A | D8: ChatGPT-4o | E8: Cấu hình BrowserRouter với Routes: trang chủ, danh sách xe, so sánh xe, chi tiết xe và admin dashboard | F8: src/App.jsx | G8: High | H8: Tích hợp React Router, bảo vệ route admin bằng ProtectedRoute | I8: Các trang điều hướng mượt mà, URL thay đổi đúng mong muốn
B9: 09/06/2026 | C9: C | D9: ChatGPT-4o | E9: Sử dụng useParams() đọc ID từ URL để fetch thông tin xe động | F9: src/pages/CarDetailPage.jsx | G9: Medium | H9: Xây dựng trang chi tiết xe CarDetailPage hiển thị thông số và ảnh lớn | I9: Truy cập /cars/6 hiển thị đúng Bugatti Tourbillon
B10: 10/06/2026 | C10: D | D10: Claude | E10: Xây dựng trang Dashboard quản trị hiển thị danh sách xe và lượt xem | F10: src/pages/AdminDashboard.jsx | G10: Medium | H10: Tạo AdminDashboard hiển thị tổng quan thông số showroom | I10: Giao diện dashboard gọn gàng, bảo mật tốt
B11: 10/06/2026 | C11: A | D11: ChatGPT-4o | E11: Redesign toàn bộ giao diện danh sách xe và so sánh xe sang glossy dark glass | F11: src/pages/CarListPage.css | G11: High | H11: Tinh chỉnh khoảng cách padding đầu trang từ 56px xuống 24px, thêm hover glow | I11: Trang list và compare trông sang trọng hơn hẳn
B17: 📝 BẢNG 2: Nhật ký thay đổi project (CHANGELOG)
B18: Added = thêm mới | Changed = cải tiến | Fixed = sửa lỗi | Removed = xóa bỏ
B19: Loại (*) | C19: TV (*) | D19: Mô tả thay đổi (*) | G19: File liên quan | I19: Ghi chú
B20: Added — Thêm mới
C21: A | D21: Cấu hình React Router v6 và định tuyến các trang trong dự án | G21: App.jsx | I21: Routing structure
C22: A | D22: Tạo ProtectedRoute.jsx bảo vệ trang quản trị admin | G22: ProtectedRoute.jsx | I22: Authentication guard
C23: C | D23: Tạo CarDetailPage.jsx và CarDetailPage.css hiển thị chi tiết động | G23: CarDetailPage.jsx | I23: Dynamic params details
B24: Changed — Cải tiến
C25: D | D25: Tạo AdminDashboard.jsx hiển thị thống kê lượt xem showroom | G25: AdminDashboard.jsx | I25: Admin control panel
C26: A | D26: Redesign toàn bộ giao diện so sánh và danh sách xe theo phong cách đen óng ánh glossy dark glass | G26: CarListPage.css, ComparePage.css | I26: Polish UI/UX
B28: Fixed — Sửa lỗi
C29: A | D29: Sửa lỗi route trùng lặp và lỗi cuộn trang khi chuyển hướng | G29: App.jsx | I29: ScrollToTop logic
C30: C | D30: Sửa lỗi ảnh placeholder áo thun trên Bugatti Tourbillon bằng ảnh Bugatti thực tế | G30: src/data/cars.js, db.json | I30: Fixed placeholder assets
B32: Removed — Xóa bỏ
B37: 💡 BẢNG 3: Nhật ký Prompt AI (PROMPTS)
B38: Mỗi prompt quan trọng ghi 1 block gồm 4 dòng. Ghi rõ prompt đã dùng, kết quả, cách nhóm sử dụng, và kiểm chứng.
B39: Prompt # | C39: TV | D39: Công cụ AI | E39: Prompt đã dùng (nguyên văn) (*)
B40: Prompt #1 (A — ChatGPT-4o) | E40: Configure React Router v6 in App.jsx. Define routes for: "/" (HomePage), "/cars" (CarListPage), "/cars/:id" (CarDetailPage), "/compare" (ComparePage), "/admin" (AdminDashboard, protected by ProtectedRoute), "/login" (LoginPage).
B41: Kết quả AI trả về và vấn đề gặp phải: | E41: AI đề xuất cấu hình React Router v5 cũ (sử dụng Switch thay vì Routes).
B42: Nhóm đã chỉnh sửa / sử dụng như thế nào: | E42: Chuyển đổi sang cấu hình v6 mới, sử dụng element={<Component />} và Outlet.
B43: Kiểm chứng (test pass/fail, kết quả đúng không): | E43: Ứng dụng chuyển đổi giữa các trang trơn tru, hiển thị đúng URL path.
B44: Prompt #2 (C — ChatGPT-4o) | E44: Write a React component for CarDetailPage. It should read the "id" param from useParams(), find the corresponding car object from mock data, and display its image and spec table.
B45: Kết quả AI trả về và vấn đề gặp phải: | E45: AI không xử lý trường hợp ID xe không tồn tại trong danh sách, gây crash màn hình.
B46: Nhóm đã chỉnh sửa / sử dụng như thế nào: | E46: Bổ dung điều kiện kiểm tra: if (!car) render thông báo "Không tìm thấy xe" kèm nút quay lại.
B47: Kiểm chứng (test pass/fail, kết quả đúng không): | E47: Truy cập link xe hợp lệ hiển thị đủ chi tiết; truy cập ID sai hiển thị thông báo lỗi.
B48: Prompt #3 (D — Claude) | E48: Create a ProtectedRoute component in React that checks localStorage for a token. If the token exists, render the children; otherwise, redirect to "/login" using Navigate.
B49: Kết quả AI trả về và vấn đề gặp phải: | E49: Claude sử dụng redirect() của react-router-dom là hàm không dùng được trong component render.
B50: Nhóm đã chỉnh sửa / sử dụng như thế nào: | E50: Thay thế bằng component <Navigate to="/login" replace /> đúng chuẩn v6.
B51: Kiểm chứng (test pass/fail, kết quả đúng không): | E51: Cố gắng truy cập trang /admin khi chưa đăng nhập sẽ tự động chuyển hướng về /login.
... B55: Kiểm chứng (test pass/fail, kết quả đúng không): | E55: Đạt hiệu ứng đen óng ánh tinh xảo, có chiều sâu, tạo cảm giác sang trọng đẳng cấp.
B57: 🪞 BẢNG 4: Suy ngẫm cuối tuần (REFLECTION)
B58: Mỗi thành viên điền 1 block riêng. Mục 'AI sai/thiếu' bắt buộc ≥ 2 ví dụ cụ thể. Viết thành câu đầy đủ.
B59: Thành viên A — Trưởng nhóm
B60: Đã làm gì trong tuần này? (*) | E60: Cấu hình React Router, code ProtectedRoute, redesign giao diện đen óng ánh glossy dark glass.
B61: AI đã hỗ trợ như thế nào? | E61: AI hỗ trợ viết các thuộc tính CSS gradient và viền glassmorphism cực kỳ bắt mắt.
B62: AI sai hoặc thiếu ở đâu? (*) | E62: (1) AI dùng cấu trúc React Router v5 đã lỗi thời. (2) Gợi ý sai cách import Navigate.
B63: Khó khăn gặp phải | E63: Giải quyết xung đột file App.jsx khi merge code định tuyến của các thành viên khác.
B64: Nếu làm lại, sẽ cải thiện điều gì? | E64: Sử dụng Git merge công cụ giải quyết thủ công cẩn thận để giữ nguyên code chức năng.
B66: Thành viên B — Thành viên
B67: Đã làm gì trong tuần này? (*) | E67: Hỗ trợ redesign, tối ưu hóa các card siêu xe khi hover nâng nhẹ và zoom ảnh.
B68: AI đã hỗ trợ như thế nào? | E68: Copilot gợi ý các thuộc tính transform và transition rất mượt mà.
B69: AI sai hoặc thiếu ở đâu? (*) | E69: (1) Hiệu ứng zoom ảnh bị tràn ra ngoài card xe — phải thêm overflow: hidden. (2) Hover bị giật trên Safari.
B70: Khó khăn gặp phải | E70: Làm cho các hover animations phản hồi nhanh nhạy nhưng vẫn êm ái.
B71: Nếu làm lại, sẽ cải thiện điều gì? | E71: Sử dụng transition: transform 0.4s cubic-bezier(0.16, 1, 0.3, 1) để tạo cảm giác cao cấp.
B73: Thành viên C — Thành viên
B74: Đã làm gì trong tuần này? (*) | E74: Code trang CarDetailPage lấy ID động, thay ảnh Bugatti thực tế từ Unsplash.
B75: AI đã hỗ trợ như thế nào? | E75: AI giúp viết mã binding dữ liệu xe dựa trên tham số URL rất nhanh gọn.
B76: AI sai hoặc thiếu ở đâu? (*) | E76: (1) AI quên convert tham số id từ string sang number trước khi so sánh ID. (2) Ảnh Bugatti bị hỏng link.
B77: Khó khăn gặp phải | E77: Tìm kiếm hình ảnh Bugatti Tourbillon chất lượng cao, đúng góc chụp studio để phối cảnh.
B78: Nếu làm lại, sẽ cải thiện điều gì? | E78: Sử dụng các ảnh thô chất lượng cao từ các trang chuyên nghiệp như Unsplash hoặc Tinh Tế.
B80: Thành viên D — Thành viên
B81: Đã làm gì trong tuần này? (*) | E81: Code AdminDashboard, thiết lập giao diện thống kê quản trị.
B82: AI đã hỗ trợ như thế nào? | E82: Claude gợi ý cách hiển thị các bảng thống kê và biểu đồ cột giả định trực quan.
B83: AI sai hoặc thiếu ở đâu? (*) | E83: (1) Bảng thống kê bị lỗi khi màn hình thu nhỏ. (2) Màu sắc biểu đồ lệch khỏi tone gold champagne.
B84: Khó khăn gặp phải | E84: Bảo mật trang Dashboard quản trị, ngăn chặn truy cập trái phép.
B85: Nếu làm lại, sẽ cải thiện điều gì? | E85: Đồng bộ token đăng nhập giả lập trong localStorage khi người dùng đăng nhập thành công.
B87: Thành viên E — Thành viên
B88: Đã làm gì trong tuần này? (*) | E88: Viết tài liệu mô tả công việc tuần 6, kiểm tra hoạt động routing.
B89: AI đã hỗ trợ như thế nào? | E89: AI giúp tóm tắt công việc chi tiết của từng người từ tuần 1 đến tuần 6 khoa học.
B90: AI sai hoặc thiếu ở đâu? (*) | E90: (1) AI viết sai mô tả vai trò của Sang. (2) Bỏ qua mô tả phần ProtectedRoute.
B91: Khó khăn gặp phải | E91: Đảm bảo tất cả các liên kết trong ứng dụng hoạt động không có lỗi 404.
B92: Nếu làm lại, sẽ cải thiện điều gì? | E92: Viết script kiểm tra tự động các link chuyển hướng để rút ngắn thời gian test thủ công.
B94: FER202 | Week 06 | FPT University — Điền xong nhớ Ctrl+S để lưu!

Sheet Week_07
B2: WEEK 01 — Nhật ký AI & Project
B3: Mỗi thành viên dùng ký hiệu A/B/C/D/E ở cột TV. Cột (*) bắt buộc điền. Lưu file sau khi điền xong.
B5: 📋 BẢNG 1: Nhật ký sử dụng AI (AI_AUDIT_LOG)
B6: Ghi mỗi lần dùng AI vào 1 dòng. Mức hỗ trợ: Low = AI gợi ý nhỏ | Medium = AI đóng góp nhiều | High = AI tạo phần lớn
B7: Ngày (*) | C7: TV (*) | D7: Công cụ AI (*) | E7: Mục đích sử dụng (*) | F7: File ảnh hưởng | G7: Mức hỗ trợ (*) | H7: Đã chỉnh sửa gì? | I7: Kiểm chứng
B17: 📝 BẢNG 2: Nhật ký thay đổi project (CHANGELOG)
B18: Added = thêm mới | Changed = cải tiến | Fixed = sửa lỗi | Removed = xóa bỏ
B19: Loại (*) | C19: TV (*) | D19: Mô tả thay đổi (*) | G19: File liên quan | I19: Ghi chú
B20: Added — Thêm mới
B24: Changed — Cải tiến
B28: Fixed — Sửa lỗi
B32: Removed — Xóa bỏ
B37: 💡 BẢNG 3: Nhật ký Prompt AI (PROMPTS)
B38: Mỗi prompt quan trọng ghi 1 block gồm 4 dòng. Ghi rõ prompt đã dùng, kết quả, cách nhóm sử dụng, và kiểm chứng.
B39: Prompt # | C39: TV | D39: Công cụ AI | E39: Prompt đã dùng (nguyên văn) (*)
B40: Prompt #1
B41: Kết quả AI trả về và vấn đề gặp phải:
B42: Nhóm đã chỉnh sửa / sử dụng như thế nào:
B43: Kiểm chứng (test pass/fail, kết quả đúng không):
B44: Prompt #2
B45: Kết quả AI trả về và vấn đề gặp phải:
B46: Nhóm đã chỉnh sửa / sử dụng như thế nào:
B47: Kiểm chứng (test pass/fail, kết quả đúng không):
B48: Prompt #3
B49: Kết quả AI trả về và vấn đề gặp phải:
B50: Nhóm đã chỉnh sửa / sử dụng như thế nào:
B51: Kiểm chứng (test pass/fail, kết quả đúng không):
... B59: Thành viên A — Trưởng nhóm
B60: Đã làm gì trong tuần này? (*) | E60: 💬 Liệt kê cụ thể: tính năng, test case, module, file...
B61: AI đã hỗ trợ như thế nào? | E61: 💬 Tóm tắt cách dùng AI: tool nào, việc gì, hiệu quả ra sao
B62: AI sai hoặc thiếu ở đâu? (*) | E62: 💬 ⚠️ Bắt buộc ≥ 2 ví dụ cụ thể về điểm AI chưa đúng/đủ
B63: Khó khăn gặp phải | E63: 💬 Kỹ thuật, nhóm, công cụ, môi trường...
B64: Nếu làm lại, sẽ cải thiện điều gì? | E64: 💬 Quy trình, cách dùng AI, phân công nhóm...
B66: Thành viên B — Thành viên
B67: Đã làm gì trong tuần này? (*) | E67: 💬 Liệt kê cụ thể: tính năng, test case, module, file...
B68: AI đã hỗ trợ như thế nào? | E68: 💬 Tóm tắt cách dùng AI: tool nào, việc gì, hiệu quả ra sao
B69: AI sai hoặc thiếu ở đâu? (*) | E69: 💬 ⚠️ Bắt buộc ≥ 2 ví dụ cụ thể về điểm AI chưa đúng/đủ
B70: Khó khăn gặp phải | E70: 💬 Kỹ thuật, nhóm, công cụ, môi trường...
B71: Nếu làm lại, sẽ cải thiện điều gì? | E71: 💬 Quy trình, cách dùng AI, phân công nhóm...
B73: Thành viên C — Thành viên
B74: Đã làm gì trong tuần này? (*) | E74: 💬 Liệt kê cụ thể: tính năng, test case, module, file...
B75: AI đã hỗ trợ như thế nào? | E75: 💬 Tóm tắt cách dùng AI: tool nào, việc gì, hiệu quả ra sao
B76: AI sai hoặc thiếu ở đâu? (*) | E76: 💬 ⚠️ Bắt buộc ≥ 2 ví dụ cụ thể về điểm AI chưa đúng/đủ
B77: Khó khăn gặp phải | E77: 💬 Kỹ thuật, nhóm, công cụ, môi trường...
B78: Nếu làm lại, sẽ cải thiện điều gì? | E78: 💬 Quy trình, cách dùng AI, phân công nhóm...
B80: Thành viên D — Thành viên
B81: Đã làm gì trong tuần này? (*) | E81: 💬 Liệt kê cụ thể: tính năng, test case, module, file...
B82: AI đã hỗ trợ như thế nào? | E82: 💬 Tóm tắt cách dùng AI: tool nào, việc gì, hiệu quả ra sao
B83: AI sai hoặc thiếu ở đâu? (*) | E83: 💬 ⚠️ Bắt buộc ≥ 2 ví dụ cụ thể về điểm AI chưa đúng/đủ
B84: Khó khăn gặp phải | E84: 💬 Kỹ thuật, nhóm, công cụ, môi trường...
B85: Nếu làm lại, sẽ cải thiện điều gì? | E85: 💬 Quy trình, cách dùng AI, phân công nhóm...
B87: Thành viên E — Thành viên
B88: Đã làm gì trong tuần này? (*) | E88: 💬 Liệt kê cụ thể: tính năng, test case, module, file...
B89: AI đã hỗ trợ như thế nào? | E89: 💬 Tóm tắt cách dùng AI: tool nào, việc gì, hiệu quả ra sao
B90: AI sai hoặc thiếu ở đâu? (*) | E90: 💬 ⚠️ Bắt buộc ≥ 2 ví dụ cụ thể về điểm AI chưa đúng/đủ
B91: Khó khăn gặp phải | E91: 💬 Kỹ thuật, nhóm, công cụ, môi trường...
B92: Nếu làm lại, sẽ cải thiện điều gì? | E92: 💬 Quy trình, cách dùng AI, phân công nhóm...
B94: FER202 | Week 07 | FPT University — Điền xong nhớ Ctrl+S để lưu!

Sheet Week_08
B2: WEEK 01 — Nhật ký AI & Project
B3: Mỗi thành viên dùng ký hiệu A/B/C/D/E ở cột TV. Cột (*) bắt buộc điền. Lưu file sau khi điền xong.
B5: 📋 BẢNG 1: Nhật ký sử dụng AI (AI_AUDIT_LOG)
B6: Ghi mỗi lần dùng AI vào 1 dòng. Mức hỗ trợ: Low = AI gợi ý nhỏ | Medium = AI đóng góp nhiều | High = AI tạo phần lớn
B7: Ngày (*) | C7: TV (*) | D7: Công cụ AI (*) | E7: Mục đích sử dụng (*) | F7: File ảnh hưởng | G7: Mức hỗ trợ (*) | H7: Đã chỉnh sửa gì? | I7: Kiểm chứng
B17: 📝 BẢNG 2: Nhật ký thay đổi project (CHANGELOG)
B18: Added = thêm mới | Changed = cải tiến | Fixed = sửa lỗi | Removed = xóa bỏ
B19: Loại (*) | C19: TV (*) | D19: Mô tả thay đổi (*) | G19: File liên quan | I19: Ghi chú
B20: Added — Thêm mới
B24: Changed — Cải tiến
B28: Fixed — Sửa lỗi
B32: Removed — Xóa bỏ
B37: 💡 BẢNG 3: Nhật ký Prompt AI (PROMPTS)
B38: Mỗi prompt quan trọng ghi 1 block gồm 4 dòng. Ghi rõ prompt đã dùng, kết quả, cách nhóm sử dụng, và kiểm chứng.
B39: Prompt # | C39: TV | D39: Công cụ AI | E39: Prompt đã dùng (nguyên văn) (*)
B40: Prompt #1
B41: Kết quả AI trả về và vấn đề gặp phải:
B42: Nhóm đã chỉnh sửa / sử dụng như thế nào:
B43: Kiểm chứng (test pass/fail, kết quả đúng không):
B44: Prompt #2
B45: Kết quả AI trả về và vấn đề gặp phải:
B46: Nhóm đã chỉnh sửa / sử dụng như thế nào:
B47: Kiểm chứng (test pass/fail, kết quả đúng không):
B48: Prompt #3
B49: Kết quả AI trả về và vấn đề gặp phải:
B50: Nhóm đã chỉnh sửa / sử dụng như thế nào:
B51: Kiểm chứng (test pass/fail, kết quả đúng không):
... B59: Thành viên A — Trưởng nhóm
B60: Đã làm gì trong tuần này? (*) | E60: 💬 Liệt kê cụ thể: tính năng, test case, module, file...
B61: AI đã hỗ trợ như thế nào? | E61: 💬 Tóm tắt cách dùng AI: tool nào, việc gì, hiệu quả ra sao
B62: AI sai hoặc thiếu ở đâu? (*) | E62: 💬 ⚠️ Bắt buộc ≥ 2 ví dụ cụ thể về điểm AI chưa đúng/đủ
B63: Khó khăn gặp phải | E63: 💬 Kỹ thuật, nhóm, công cụ, môi trường...
B64: Nếu làm lại, sẽ cải thiện điều gì? | E64: 💬 Quy trình, cách dùng AI, phân công nhóm...
B66: Thành viên B — Thành viên
B67: Đã làm gì trong tuần này? (*) | E67: 💬 Liệt kê cụ thể: tính năng, test case, module, file...
B68: AI đã hỗ trợ như thế nào? | E68: 💬 Tóm tắt cách dùng AI: tool nào, việc gì, hiệu quả ra sao
B69: AI sai hoặc thiếu ở đâu? (*) | E69: 💬 ⚠️ Bắt buộc ≥ 2 ví dụ cụ thể về điểm AI chưa đúng/đủ
B70: Khó khăn gặp phải | E70: 💬 Kỹ thuật, nhóm, công cụ, môi trường...
B71: Nếu làm lại, sẽ cải thiện điều gì? | E71: 💬 Quy trình, cách dùng AI, phân công nhóm...
B73: Thành viên C — Thành viên
B74: Đã làm gì trong tuần này? (*) | E74: 💬 Liệt kê cụ thể: tính năng, test case, module, file...
B75: AI đã hỗ trợ như thế nào? | E75: 💬 Tóm tắt cách dùng AI: tool nào, việc gì, hiệu quả ra sao
B76: AI sai hoặc thiếu ở đâu? (*) | E76: 💬 ⚠️ Bắt buộc ≥ 2 ví dụ cụ thể về điểm AI chưa đúng/đủ
B77: Khó khăn gặp phải | E77: 💬 Kỹ thuật, nhóm, công cụ, môi trường...
B78: Nếu làm lại, sẽ cải thiện điều gì? | E78: 💬 Quy trình, cách dùng AI, phân công nhóm...
B80: Thành viên D — Thành viên
B81: Đã làm gì trong tuần này? (*) | E81: 💬 Liệt kê cụ thể: tính năng, test case, module, file...
B82: AI đã hỗ trợ như thế nào? | E82: 💬 Tóm tắt cách dùng AI: tool nào, việc gì, hiệu quả ra sao
B83: AI sai hoặc thiếu ở đâu? (*) | E83: 💬 ⚠️ Bắt buộc ≥ 2 ví dụ cụ thể về điểm AI chưa đúng/đủ
B84: Khó khăn gặp phải | E84: 💬 Kỹ thuật, nhóm, công cụ, môi trường...
B85: Nếu làm lại, sẽ cải thiện điều gì? | E85: 💬 Quy trình, cách dùng AI, phân công nhóm...
B87: Thành viên E — Thành viên
B88: Đã làm gì trong tuần này? (*) | E88: 💬 Liệt kê cụ thể: tính năng, test case, module, file...
B89: AI đã hỗ trợ như thế nào? | E89: 💬 Tóm tắt cách dùng AI: tool nào, việc gì, hiệu quả ra sao
B90: AI sai hoặc thiếu ở đâu? (*) | E90: 💬 ⚠️ Bắt buộc ≥ 2 ví dụ cụ thể về điểm AI chưa đúng/đủ
B91: Khó khăn gặp phải | E91: 💬 Kỹ thuật, nhóm, công cụ, môi trường...
B92: Nếu làm lại, sẽ cải thiện điều gì? | E92: 💬 Quy trình, cách dùng AI, phân công nhóm...
B94: FER202 | Week 08 | FPT University — Điền xong nhớ Ctrl+S để lưu!

Sheet Week_09
B2: WEEK 01 — Nhật ký AI & Project
B3: Mỗi thành viên dùng ký hiệu A/B/C/D/E ở cột TV. Cột (*) bắt buộc điền. Lưu file sau khi điền xong.
B5: 📋 BẢNG 1: Nhật ký sử dụng AI (AI_AUDIT_LOG)
B6: Ghi mỗi lần dùng AI vào 1 dòng. Mức hỗ trợ: Low = AI gợi ý nhỏ | Medium = AI đóng góp nhiều | High = AI tạo phần lớn
B7: Ngày (*) | C7: TV (*) | D7: Công cụ AI (*) | E7: Mục đích sử dụng (*) | F7: File ảnh hưởng | G7: Mức hỗ trợ (*) | H7: Đã chỉnh sửa gì? | I7: Kiểm chứng
B17: 📝 BẢNG 2: Nhật ký thay đổi project (CHANGELOG)
B18: Added = thêm mới | Changed = cải tiến | Fixed = sửa lỗi | Removed = xóa bỏ
B19: Loại (*) | C19: TV (*) | D19: Mô tả thay đổi (*) | G19: File liên quan | I19: Ghi chú
B20: Added — Thêm mới
B24: Changed — Cải tiến
B28: Fixed — Sửa lỗi
B32: Removed — Xóa bỏ
B37: 💡 BẢNG 3: Nhật ký Prompt AI (PROMPTS)
B38: Mỗi prompt quan trọng ghi 1 block gồm 4 dòng. Ghi rõ prompt đã dùng, kết quả, cách nhóm sử dụng, và kiểm chứng.
B39: Prompt # | C39: TV | D39: Công cụ AI | E39: Prompt đã dùng (nguyên văn) (*)
B40: Prompt #1
B41: Kết quả AI trả về và vấn đề gặp phải:
B42: Nhóm đã chỉnh sửa / sử dụng như thế nào:
B43: Kiểm chứng (test pass/fail, kết quả đúng không):
B44: Prompt #2
B45: Kết quả AI trả về và vấn đề gặp phải:
B46: Nhóm đã chỉnh sửa / sử dụng như thế nào:
B47: Kiểm chứng (test pass/fail, kết quả đúng không):
B48: Prompt #3
B49: Kết quả AI trả về và vấn đề gặp phải:
B50: Nhóm đã chỉnh sửa / sử dụng như thế nào:
B51: Kiểm chứng (test pass/fail, kết quả đúng không):
... B59: Thành viên A — Trưởng nhóm
B60: Đã làm gì trong tuần này? (*) | E60: 💬 Liệt kê cụ thể: tính năng, test case, module, file...
B61: AI đã hỗ trợ như thế nào? | E61: 💬 Tóm tắt cách dùng AI: tool nào, việc gì, hiệu quả ra sao
B62: AI sai hoặc thiếu ở đâu? (*) | E62: 💬 ⚠️ Bắt buộc ≥ 2 ví dụ cụ thể về điểm AI chưa đúng/đủ
B63: Khó khăn gặp phải | E63: 💬 Kỹ thuật, nhóm, công cụ, môi trường...
B64: Nếu làm lại, sẽ cải thiện điều gì? | E64: 💬 Quy trình, cách dùng AI, phân công nhóm...
B66: Thành viên B — Thành viên
B67: Đã làm gì trong tuần này? (*) | E67: 💬 Liệt kê cụ thể: tính năng, test case, module, file...
B68: AI đã hỗ trợ như thế nào? | E68: 💬 Tóm tắt cách dùng AI: tool nào, việc gì, hiệu quả ra sao
B69: AI sai hoặc thiếu ở đâu? (*) | E69: 💬 ⚠️ Bắt buộc ≥ 2 ví dụ cụ thể về điểm AI chưa đúng/đủ
B70: Khó khăn gặp phải | E70: 💬 Kỹ thuật, nhóm, công cụ, môi trường...
B71: Nếu làm lại, sẽ cải thiện điều gì? | E71: 💬 Quy trình, cách dùng AI, phân công nhóm...
B73: Thành viên C — Thành viên
B74: Đã làm gì trong tuần này? (*) | E74: 💬 Liệt kê cụ thể: tính năng, test case, module, file...
B75: AI đã hỗ trợ như thế nào? | E75: 💬 Tóm tắt cách dùng AI: tool nào, việc gì, hiệu quả ra sao
B76: AI sai hoặc thiếu ở đâu? (*) | E76: 💬 ⚠️ Bắt buộc ≥ 2 ví dụ cụ thể về điểm AI chưa đúng/đủ
B77: Khó khăn gặp phải | E77: 💬 Kỹ thuật, nhóm, công cụ, môi trường...
B78: Nếu làm lại, sẽ cải thiện điều gì? | E78: 💬 Quy trình, cách dùng AI, phân công nhóm...
B80: Thành viên D — Thành viên
B81: Đã làm gì trong tuần này? (*) | E81: 💬 Liệt kê cụ thể: tính năng, test case, module, file...
B82: AI đã hỗ trợ như thế nào? | E82: 💬 Tóm tắt cách dùng AI: tool nào, việc gì, hiệu quả ra sao
B83: AI sai hoặc thiếu ở đâu? (*) | E83: 💬 ⚠️ Bắt buộc ≥ 2 ví dụ cụ thể về điểm AI chưa đúng/đủ
B84: Khó khăn gặp phải | E84: 💬 Kỹ thuật, nhóm, công cụ, môi trường...
B85: Nếu làm lại, sẽ cải thiện điều gì? | E85: 💬 Quy trình, cách dùng AI, phân công nhóm...
B87: Thành viên E — Thành viên
B88: Đã làm gì trong tuần này? (*) | E88: 💬 Liệt kê cụ thể: tính năng, test case, module, file...
B89: AI đã hỗ trợ như thế nào? | E89: 💬 Tóm tắt cách dùng AI: tool nào, việc gì, hiệu quả ra sao
B90: AI sai hoặc thiếu ở đâu? (*) | E90: 💬 ⚠️ Bắt buộc ≥ 2 ví dụ cụ thể về điểm AI chưa đúng/đủ
B91: Khó khăn gặp phải | E91: 💬 Kỹ thuật, nhóm, công cụ, môi trường...
B92: Nếu làm lại, sẽ cải thiện điều gì? | E92: 💬 Quy trình, cách dùng AI, phân công nhóm...
B94: FER202 | Week 09 | FPT University — Điền xong nhớ Ctrl+S để lưu!

Sheet Week_10
B2: WEEK 01 — Nhật ký AI & Project
B3: Mỗi thành viên dùng ký hiệu A/B/C/D/E ở cột TV. Cột (*) bắt buộc điền. Lưu file sau khi điền xong.
B5: 📋 BẢNG 1: Nhật ký sử dụng AI (AI_AUDIT_LOG)
B6: Ghi mỗi lần dùng AI vào 1 dòng. Mức hỗ trợ: Low = AI gợi ý nhỏ | Medium = AI đóng góp nhiều | High = AI tạo phần lớn
B7: Ngày (*) | C7: TV (*) | D7: Công cụ AI (*) | E7: Mục đích sử dụng (*) | F7: File ảnh hưởng | G7: Mức hỗ trợ (*) | H7: Đã chỉnh sửa gì? | I7: Kiểm chứng
B17: 📝 BẢNG 2: Nhật ký thay đổi project (CHANGELOG)
B18: Added = thêm mới | Changed = cải tiến | Fixed = sửa lỗi | Removed = xóa bỏ
B19: Loại (*) | C19: TV (*) | D19: Mô tả thay đổi (*) | G19: File liên quan | I19: Ghi chú
B20: Added — Thêm mới
B24: Changed — Cải tiến
B28: Fixed — Sửa lỗi
B32: Removed — Xóa bỏ
B37: 💡 BẢNG 3: Nhật ký Prompt AI (PROMPTS)
B38: Mỗi prompt quan trọng ghi 1 block gồm 4 dòng. Ghi rõ prompt đã dùng, kết quả, cách nhóm sử dụng, và kiểm chứng.
B39: Prompt # | C39: TV | D39: Công cụ AI | E39: Prompt đã dùng (nguyên văn) (*)
B40: Prompt #1
B41: Kết quả AI trả về và vấn đề gặp phải:
B42: Nhóm đã chỉnh sửa / sử dụng như thế nào:
B43: Kiểm chứng (test pass/fail, kết quả đúng không):
B44: Prompt #2
B45: Kết quả AI trả về và vấn đề gặp phải:
B46: Nhóm đã chỉnh sửa / sử dụng như thế nào:
B47: Kiểm chứng (test pass/fail, kết quả đúng không):
B48: Prompt #3
B49: Kết quả AI trả về và vấn đề gặp phải:
B50: Nhóm đã chỉnh sửa / sử dụng như thế nào:
B51: Kiểm chứng (test pass/fail, kết quả đúng không):
... B59: Thành viên A — Trưởng nhóm
B60: Đã làm gì trong tuần này? (*) | E60: 💬 Liệt kê cụ thể: tính năng, test case, module, file...
B61: AI đã hỗ trợ như thế nào? | E61: 💬 Tóm tắt cách dùng AI: tool nào, việc gì, hiệu quả ra sao
B62: AI sai hoặc thiếu ở đâu? (*) | E62: 💬 ⚠️ Bắt buộc ≥ 2 ví dụ cụ thể về điểm AI chưa đúng/đủ
B63: Khó khăn gặp phải | E63: 💬 Kỹ thuật, nhóm, công cụ, môi trường...
B64: Nếu làm lại, sẽ cải thiện điều gì? | E64: 💬 Quy trình, cách dùng AI, phân công nhóm...
B66: Thành viên B — Thành viên
B67: Đã làm gì trong tuần này? (*) | E67: 💬 Liệt kê cụ thể: tính năng, test case, module, file...
B68: AI đã hỗ trợ như thế nào? | E68: 💬 Tóm tắt cách dùng AI: tool nào, việc gì, hiệu quả ra sao
B69: AI sai hoặc thiếu ở đâu? (*) | E69: 💬 ⚠️ Bắt buộc ≥ 2 ví dụ cụ thể về điểm AI chưa đúng/đủ
B70: Khó khăn gặp phải | E70: 💬 Kỹ thuật, nhóm, công cụ, môi trường...
B71: Nếu làm lại, sẽ cải thiện điều gì? | E71: 💬 Quy trình, cách dùng AI, phân công nhóm...
B73: Thành viên C — Thành viên
B74: Đã làm gì trong tuần này? (*) | E74: 💬 Liệt kê cụ thể: tính năng, test case, module, file...
B75: AI đã hỗ trợ như thế nào? | E75: 💬 Tóm tắt cách dùng AI: tool nào, việc gì, hiệu quả ra sao
B76: AI sai hoặc thiếu ở đâu? (*) | E76: 💬 ⚠️ Bắt buộc ≥ 2 ví dụ cụ thể về điểm AI chưa đúng/đủ
B77: Khó khăn gặp phải | E77: 💬 Kỹ thuật, nhóm, công cụ, môi trường...
B78: Nếu làm lại, sẽ cải thiện điều gì? | E78: 💬 Quy trình, cách dùng AI, phân công nhóm...
B80: Thành viên D — Thành viên
B81: Đã làm gì trong tuần này? (*) | E81: 💬 Liệt kê cụ thể: tính năng, test case, module, file...
B82: AI đã hỗ trợ như thế nào? | E82: 💬 Tóm tắt cách dùng AI: tool nào, việc gì, hiệu quả ra sao
B83: AI sai hoặc thiếu ở đâu? (*) | E83: 💬 ⚠️ Bắt buộc ≥ 2 ví dụ cụ thể về điểm AI chưa đúng/đủ
B84: Khó khăn gặp phải | E84: 💬 Kỹ thuật, nhóm, công cụ, môi trường...
B85: Nếu làm lại, sẽ cải thiện điều gì? | E85: 💬 Quy trình, cách dùng AI, phân công nhóm...
B87: Thành viên E — Thành viên
B88: Đã làm gì trong tuần này? (*) | E88: 💬 Liệt kê cụ thể: tính năng, test case, module, file...
B89: AI đã hỗ trợ như thế nào? | E89: 💬 Tóm tắt cách dùng AI: tool nào, việc gì, hiệu quả ra sao
B90: AI sai hoặc thiếu ở đâu? (*) | E90: 💬 ⚠️ Bắt buộc ≥ 2 ví dụ cụ thể về điểm AI chưa đúng/đủ
B91: Khó khăn gặp phải | E91: 💬 Kỹ thuật, nhóm, công cụ, môi trường...
B92: Nếu làm lại, sẽ cải thiện điều gì? | E92: 💬 Quy trình, cách dùng AI, phân công nhóm...
B94: FER202 | Week 10 | FPT University — Điền xong nhớ Ctrl+S để lưu!

Sheet Summary
B2: SUMMARY — Tổng hợp cả học kỳ
B4: 📊 Tổng số lần dùng AI theo tuần & thành viên (tự động đếm từ các sheet Week)
B5: Tuần | C5: TV-A | D5: TV-B | E5: TV-C | F5: TV-D | G5: TV-E | H5: Tổng | I5: Low | J5: Medium | K5: High | L5: Ghi chú
B6: Week 01 | C6: =COUNTIF(Week_01!$C$8:$C$15,"A") | D6: =COUNTIF(Week_01!$C$8:$C$15,"B") | E6: =COUNTIF(Week_01!$C$8:$C$15,"C") | F6: =COUNTIF(Week_01!$C$8:$C$15,"D") | G6: =COUNTIF(Week_01!$C$8:$C$15,"E") | H6: =SUM(C6:G6) | I6: =COUNTIF(Week_01!$G$8:$G$15,"Low") | J6: =COUNTIF(Week_01!$G$8:$G$15,"Medium") | K6: =COUNTIF(Week_01!$G$8:$G$15,"High")
B7: Week 02 | C7: =COUNTIF(Week_02!$C$8:$C$15,"A") | D7: =COUNTIF(Week_02!$C$8:$C$15,"B") | E7: =COUNTIF(Week_02!$C$8:$C$15,"C") | F7: =COUNTIF(Week_02!$C$8:$C$15,"D") | G7: =COUNTIF(Week_02!$C$8:$C$15,"E") | H7: =SUM(C7:G7) | I7: =COUNTIF(Week_02!$G$8:$G$15,"Low") | J7: =COUNTIF(Week_02!$G$8:$G$15,"Medium") | K7: =COUNTIF(Week_02!$G$8:$G$15,"High")
B8: Week 03 | C8: =COUNTIF(Week_03!$C$8:$C$15,"A") | D8: =COUNTIF(Week_03!$C$8:$C$15,"B") | E8: =COUNTIF(Week_03!$C$8:$C$15,"C") | F8: =COUNTIF(Week_03!$C$8:$C$15,"D") | G8: =COUNTIF(Week_03!$C$8:$C$15,"E") | H8: =SUM(C8:G8) | I8: =COUNTIF(Week_03!$G$8:$G$15,"Low") | J8: =COUNTIF(Week_03!$G$8:$G$15,"Medium") | K8: =COUNTIF(Week_03!$G$8:$G$15,"High")
B9: Week 04 | C9: =COUNTIF(Week_04!$C$8:$C$15,"A") | D9: =COUNTIF(Week_04!$C$8:$C$15,"B") | E9: =COUNTIF(Week_04!$C$8:$C$15,"C") | F9: =COUNTIF(Week_04!$C$8:$C$15,"D") | G9: =COUNTIF(Week_04!$C$8:$C$15,"E") | H9: =SUM(C9:G9) | I9: =COUNTIF(Week_04!$G$8:$G$15,"Low") | J9: =COUNTIF(Week_04!$G$8:$G$15,"Medium") | K9: =COUNTIF(Week_04!$G$8:$G$15,"High")
B10: Week 05 | C10: =COUNTIF(Week_05!$C$8:$C$15,"A") | D10: =COUNTIF(Week_05!$C$8:$C$15,"B") | E10: =COUNTIF(Week_05!$C$8:$C$15,"C") | F10: =COUNTIF(Week_05!$C$8:$C$15,"D") | G10: =COUNTIF(Week_05!$C$8:$C$15,"E") | H10: =SUM(C10:G10) | I10: =COUNTIF(Week_05!$G$8:$G$15,"Low") | J10: =COUNTIF(Week_05!$G$8:$G$15,"Medium") | K10: =COUNTIF(Week_05!$G$8:$G$15,"High")
B11: Week 06 | C11: =COUNTIF(Week_06!$C$8:$C$15,"A") | D11: =COUNTIF(Week_06!$C$8:$C$15,"B") | E11: =COUNTIF(Week_06!$C$8:$C$15,"C") | F11: =COUNTIF(Week_06!$C$8:$C$15,"D") | G11: =COUNTIF(Week_06!$C$8:$C$15,"E") | H11: =SUM(C11:G11) | I11: =COUNTIF(Week_06!$G$8:$G$15,"Low") | J11: =COUNTIF(Week_06!$G$8:$G$15,"Medium") | K11: =COUNTIF(Week_06!$G$8:$G$15,"High")
B12: Week 07 | C12: =COUNTIF(Week_07!$C$8:$C$15,"A") | D12: =COUNTIF(Week_07!$C$8:$C$15,"B") | E12: =COUNTIF(Week_07!$C$8:$C$15,"C") | F12: =COUNTIF(Week_07!$C$8:$C$15,"D") | G12: =COUNTIF(Week_07!$C$8:$C$15,"E") | H12: =SUM(C12:G12) | I12: =COUNTIF(Week_07!$G$8:$G$15,"Low") | J12: =COUNTIF(Week_07!$G$8:$G$15,"Medium") | K12: =COUNTIF(Week_07!$G$8:$G$15,"High")
B13: Week 08 | C13: =COUNTIF(Week_08!$C$8:$C$15,"A") | D13: =COUNTIF(Week_08!$C$8:$C$15,"B") | E13: =COUNTIF(Week_08!$C$8:$C$15,"C") | F13: =COUNTIF(Week_08!$C$8:$C$15,"D") | G13: =COUNTIF(Week_08!$C$8:$C$15,"E") | H13: =SUM(C13:G13) | I13: =COUNTIF(Week_08!$G$8:$G$15,"Low") | J13: =COUNTIF(Week_08!$G$8:$G$15,"Medium") | K13: =COUNTIF(Week_08!$G$8:$G$15,"High")
B14: Week 09 | C14: =COUNTIF(Week_09!$C$8:$C$15,"A") | D14: =COUNTIF(Week_09!$C$8:$C$15,"B") | E14: =COUNTIF(Week_09!$C$8:$C$15,"C") | F14: =COUNTIF(Week_09!$C$8:$C$15,"D") | G14: =COUNTIF(Week_09!$C$8:$C$15,"E") | H14: =SUM(C14:G14) | I14: =COUNTIF(Week_09!$G$8:$G$15,"Low") | J14: =COUNTIF(Week_09!$G$8:$G$15,"Medium") | K14: =COUNTIF(Week_09!$G$8:$G$15,"High")
B15: Week 10 | C15: =COUNTIF(Week_10!$C$8:$C$15,"A") | D15: =COUNTIF(Week_10!$C$8:$C$15,"B") | E15: =COUNTIF(Week_10!$C$8:$C$15,"C") | F15: =COUNTIF(Week_10!$C$8:$C$15,"D") | G15: =COUNTIF(Week_10!$C$8:$C$15,"E") | H15: =SUM(C15:G15) | I15: =COUNTIF(Week_10!$G$8:$G$15,"Low") | J15: =COUNTIF(Week_10!$G$8:$G$15,"Medium") | K15: =COUNTIF(Week_10!$G$8:$G$15,"High")
B16: TỔNG | C16: =SUM(C6:C15) | D16: =SUM(D6:D15) | E16: =SUM(E6:E15) | F16: =SUM(F6:F15) | G16: =SUM(G6:G15) | H16: =SUM(H6:H15) | I16: =SUM(I6:I15) | J16: =SUM(J6:J15) | K16: =SUM(K6:K15)
B18: 📝 Nhận xét tổng kết học kỳ của nhóm
B19: Công cụ AI nhóm dùng nhiều nhất:
B20: Tuần sử dụng AI hiệu quả nhất và lý do:
B21: Điểm hạn chế / rủi ro khi dùng AI trong project:
B22: Bài học lớn nhất từ việc dùng AI trong học kỳ này:
